Workbook

Sheet Summary
A1: Summary — feature readiness by launch phase
A2: Live rollup from the Features sheet. Status column derives on-track / at-risk / blocked from the underlying data.
A4: phase | B4: features_required | C4: complete | D4: in_progress | E4: blocked | F4: not_started | G4: percent_complete | H4: status
A5: Alpha | B5: =COUNTIF('Features'!$E$3:$E$72,"Alpha") | C5: =COUNTIFS('Features'!$E$3:$E$72,"Alpha",'Features'!$G$3:$G$72,"complete") | D5: =COUNTIFS('Features'!$E$3:$E$72,"Alpha",'Features'!$G$3:$G$72,"in_progress")+COUNTIFS('Features'!$E$3:$E$72,"Alpha",'Features'!$G$3:$G$72,"in_review") | E5: =COUNTIFS('Features'!$E$3:$E$72,"Alpha",'Features'!$G$3:$G$72,"blocked") | F5: =COUNTIFS('Features'!$E$3:$E$72,"Alpha",'Features'!$G$3:$G$72,"not_started") | G5: =IFERROR(ROUND(SUMIFS('Features'!$H$3:$H$72,'Features'!$E$3:$E$72,"Alpha")/(B5*100),3),0) | H5: =IF(E5>0,"BLOCKED",IF(G5>=0.9,"ON-TRACK",IF(G5>=0.5,"AT-RISK",IF(B5=0,"N/A","AT-RISK"))))
A6: Beta | B6: =COUNTIF('Features'!$E$3:$E$72,"Beta") | C6: =COUNTIFS('Features'!$E$3:$E$72,"Beta",'Features'!$G$3:$G$72,"complete") | D6: =COUNTIFS('Features'!$E$3:$E$72,"Beta",'Features'!$G$3:$G$72,"in_progress")+COUNTIFS('Features'!$E$3:$E$72,"Beta",'Features'!$G$3:$G$72,"in_review") | E6: =COUNTIFS('Features'!$E$3:$E$72,"Beta",'Features'!$G$3:$G$72,"blocked") | F6: =COUNTIFS('Features'!$E$3:$E$72,"Beta",'Features'!$G$3:$G$72,"not_started") | G6: =IFERROR(ROUND(SUMIFS('Features'!$H$3:$H$72,'Features'!$E$3:$E$72,"Beta")/(B6*100),3),0) | H6: =IF(E6>0,"BLOCKED",IF(G6>=0.9,"ON-TRACK",IF(G6>=0.5,"AT-RISK",IF(B6=0,"N/A","AT-RISK"))))
A7: GA | B7: =COUNTIF('Features'!$E$3:$E$72,"GA") | C7: =COUNTIFS('Features'!$E$3:$E$72,"GA",'Features'!$G$3:$G$72,"complete") | D7: =COUNTIFS('Features'!$E$3:$E$72,"GA",'Features'!$G$3:$G$72,"in_progress")+COUNTIFS('Features'!$E$3:$E$72,"GA",'Features'!$G$3:$G$72,"in_review") | E7: =COUNTIFS('Features'!$E$3:$E$72,"GA",'Features'!$G$3:$G$72,"blocked") | F7: =COUNTIFS('Features'!$E$3:$E$72,"GA",'Features'!$G$3:$G$72,"not_started") | G7: =IFERROR(ROUND(SUMIFS('Features'!$H$3:$H$72,'Features'!$E$3:$E$72,"GA")/(B7*100),3),0) | H7: =IF(E7>0,"BLOCKED",IF(G7>=0.9,"ON-TRACK",IF(G7>=0.5,"AT-RISK",IF(B7=0,"N/A","AT-RISK"))))
A8: Post-GA | B8: =COUNTIF('Features'!$E$3:$E$72,"Post-GA") | C8: =COUNTIFS('Features'!$E$3:$E$72,"Post-GA",'Features'!$G$3:$G$72,"complete") | D8: =COUNTIFS('Features'!$E$3:$E$72,"Post-GA",'Features'!$G$3:$G$72,"in_progress")+COUNTIFS('Features'!$E$3:$E$72,"Post-GA",'Features'!$G$3:$G$72,"in_review") | E8: =COUNTIFS('Features'!$E$3:$E$72,"Post-GA",'Features'!$G$3:$G$72,"blocked") | F8: =COUNTIFS('Features'!$E$3:$E$72,"Post-GA",'Features'!$G$3:$G$72,"not_started") | G8: =IFERROR(ROUND(SUMIFS('Features'!$H$3:$H$72,'Features'!$E$3:$E$72,"Post-GA")/(B8*100),3),0) | H8: =IF(E8>0,"BLOCKED",IF(G8>=0.9,"ON-TRACK",IF(G8>=0.5,"AT-RISK",IF(B8=0,"N/A","AT-RISK"))))
A10: Earliest blocker (first feature with status = blocked)
A11: =IFERROR(INDEX('Features'!A3:A72,MATCH("blocked",'Features'!$G$3:$G$72,0)),"None") | B11: =IFERROR(INDEX('Features'!B3:B72,MATCH("blocked",'Features'!$G$3:$G$72,0)),"None") | C11: =IFERROR(INDEX('Features'!E3:E72,MATCH("blocked",'Features'!$G$3:$G$72,0)),"") | D11: =IFERROR(INDEX('Features'!I3:I72,MATCH("blocked",'Features'!$G$3:$G$72,0)),"")

Sheet Problems
A1: Problems — the grand-vision list, mapped to features
A2: Each problem is mapped to the features that help solve it. fulfilment_status derives from the status of mapped features. alpha_testable = whether Alpha-stage features alone are enough to validate this problem with testers.
A4: problem_id | B4: problem_statement | C4: earliest_phase_solvable | D4: alpha_testable | E4: mapped_features | F4: feature_count | G4: complete_or_review_count | H4: fulfilment_status | I4: notes
A5: P-001 | B5: Generic AI doesn't know my customer deeply enough. | C5: Alpha | D5: Yes | E5: F-004,F-005,F-006,F-007,F-008,F-009,F-012,F-022,F-058,F-060 | F5: 10 | G5: =(COUNTIFS('Features'!$A$3:$A$72,"F-004",'Features'!$G$3:$G$72,"complete")+COUNTIFS('Features'!$A$3:$A$72,"F-004",'Features'!$G$3:$G$72,"in_review")+COUNTIFS('Features'!$A$3:$A$72,"F-005",'Features'!$G$3:$G$72,"complete")+COUNTIFS('Features'!$A$3:$A$72,"F-005",'Features'!$G$3:$G$72,"in_review")+COUNTIFS('Features'!$A$3:$A$72,"F-006",'Features'!$G$3:$G$72,"complete")+COUNTIFS('Features'!$A$3:$A$72,"F-006",'Features'!$G$3:$G$72,"in_review")+COUNTIFS('Features'!$A$3:$A$72,"F-007",'Features'!$G$3:$G$72,"complete")+COUNTIFS('Features'!$A$3:$A$72,"F-007",'Features'!$G$3:$G$72,"in_review")+COUNTIFS('Features'!$A$3:$A$72,"F-008",'Features'!$G$3:$G$72,"complete")+COUNTIFS('Features'!$A$3:$A$72,"F-008",'Features'!$G$3:$G$72,"in_review")+COUNTIFS('Features'!$A$3:$A$72,"F-009",'Features'!$G$3:$G$72,"complete")+COUNTIFS('Features'!$A$3:$A$72,"F-009",'Features'!$G$3:$G$72,"in_review")+COUNTIFS('Features'!$A$3:$A$72,"F-012",'Features'!$G$3:$G$72,"complete")+COUNTIFS('Features'!$A$3:$A$72,"F-012",'Features'!$G$3:$G$72,"in_review")+COUNTIFS('Features'!$A$3:$A$72,"F-022",'Features'!$G$3:$G$72,"complete")+COUNTIFS('Features'!$A$3:$A$72,"F-022",'Features'!$G$3:$G$72,"in_review")+COUNTIFS('Features'!$A$3:$A$72,"F-058",'Features'!$G$3:$G$72,"complete")+COUNTIFS('Features'!$A$3:$A$72,"F-058",'Features'!$G$3:$G$72,"in_review")+COUNTIFS('Features'!$A$3:$A$72,"F-060",'Features'!$G$3:$G$72,"complete")+COUNTIFS('Features'!$A$3:$A$72,"F-060",'Features'!$G$3:$G$72,"in_review")) | H5: =IF((COUNTIFS('Features'!$A$3:$A$72,"F-004",'Features'!$G$3:$G$72,"blocked")+COUNTIFS('Features'!$A$3:$A$72,"F-005",'Features'!$G$3:$G$72,"blocked")+COUNTIFS('Features'!$A$3:$A$72,"F-006",'Features'!$G$3:$G$72,"blocked")+COUNTIFS('Features'!$A$3:$A$72,"F-007",'Features'!$G$3:$G$72,"blocked")+COUNTIFS('Features'!$A$3:$A$72,"F-008",'Features'!$G$3:$G$72,"blocked")+COUNTIFS('Features'!$A$3:$A$72,"F-009",'Features'!$G$3:$G$72,"blocked")+COUNTIFS('Features'!$A$3:$A$72,"F-012",'Features'!$G$3:$G$72,"blocked")+COUNTIFS('Features'!$A$3:$A$72,"F-022",'Features'!$G$3:$G$72,"blocked")+COUNTIFS('Features'!$A$3:$A$72,"F-058",'Features'!$G$3:$G$72,"blocked")+COUNTIFS('Features'!$A$3:$A$72,"F-060",'Features'!$G$3:$G$72,"blocked"))>0,"BLOCKED — see mapped features",IF((COUNTIFS('Features'!$A$3:$A$72,"F-004",'Features'!$G$3:$G$72,"complete")+COUNTIFS('Features'!$A$3:$A$72,"F-004",'Features'!$G$3:$G$72,"in_review")+COUNTIFS('Features'!$A$3:$A$72,"F-005",'Features'!$G$3:$G$72,"complete")+COUNTIFS('Features'!$A$3:$A$72,"F-005",'Features'!$G$3:$G$72,"in_review")+COUNTIFS('Features'!$A$3:$A$72,"F-006",'Features'!$G$3:$G$72,"complete")+COUNTIFS('Features'!$A$3:$A$72,"F-006",'Features'!$G$3:$G$72,"in_review")+COUNTIFS('Features'!$A$3:$A$72,"F-007",'Features'!$G$3:$G$72,"complete")+COUNTIFS('Features'!$A$3:$A$72,"F-007",'Features'!$G$3:$G$72,"in_review")+COUNTIFS('Features'!$A$3:$A$72,"F-008",'Features'!$G$3:$G$72,"complete")+COUNTIFS('Features'!$A$3:$A$72,"F-008",'Features'!$G$3:$G$72,"in_review")+COUNTIFS('Features'!$A$3:$A$72,"F-009",'Features'!$G$3:$G$72,"complete")+COUNTIFS('Features'!$A$3:$A$72,"F-009",'Features'!$G$3:$G$72,"in_review")+COUNTIFS('Features'!$A$3:$A$72,"F-012",'Features'!$G$3:$G$72,"complete")+COUNTIFS('Features'!$A$3:$A$72,"F-012",'Features'!$G$3:$G$72,"in_review")+COUNTIFS('Features'!$A$3:$A$72,"F-022",'Features'!$G$3:$G$72,"complete")+COUNTIFS('Features'!$A$3:$A$72,"F-022",'Features'!$G$3:$G$72,"in_review")+COUNTIFS('Features'!$A$3:$A$72,"F-058",'Features'!$G$3:$G$72,"complete")+COUNTIFS('Features'!$A$3:$A$72,"F-058",'Features'!$G$3:$G$72,"in_review")+COUNTIFS('Features'!$A$3:$A$72,"F-060",'Features'!$G$3:$G$72,"complete")+COUNTIFS('Features'!$A$3:$A$72,"F-060",'Features'!$G$3:$G$72,"in_review"))=10,"MET",IF((COUNTIFS('Features'!$A$3:$A$72,"F-004",'Features'!$G$3:$G$72,"complete")+COUNTIFS('Features'!$A$3:$A$72,"F-004",'Features'!$G$3:$G$72,"in_review")+COUNTIFS('Features'!$A$3:$A$72,"F-005",'Features'!$G$3:$G$72,"complete")+COUNTIFS('Features'!$A$3:$A$72,"F-005",'Features'!$G$3:$G$72,"in_review")+COUNTIFS('Features'!$A$3:$A$72,"F-006",'Features'!$G$3:$G$72,"complete")+COUNTIFS('Features'!$A$3:$A$72,"F-006",'Features'!$G$3:$G$72,"in_review")+COUNTIFS('Features'!$A$3:$A$72,"F-007",'Features'!$G$3:$G$72,"complete")+COUNTIFS('Features'!$A$3:$A$72,"F-007",'Features'!$G$3:$G$72,"in_review")+COUNTIFS('Features'!$A$3:$A$72,"F-008",'Features'!$G$3:$G$72,"complete")+COUNTIFS('Features'!$A$3:$A$72,"F-008",'Features'!$G$3:$G$72,"in_review")+COUNTIFS('Features'!$A$3:$A$72,"F-009",'Features'!$G$3:$G$72,"complete")+COUNTIFS('Features'!$A$3:$A$72,"F-009",'Features'!$G$3:$G$72,"in_review")+COUNTIFS('Features'!$A$3:$A$72,"F-012",'Features'!$G$3:$G$72,"complete")+COUNTIFS('Features'!$A$3:$A$72,"F-012",'Features'!$G$3:$G$72,"in_review")+COUNTIFS('Features'!$A$3:$A$72,"F-022",'Features'!$G$3:$G$72,"complete")+COUNTIFS('Features'!$A$3:$A$72,"F-022",'Features'!$G$3:$G$72,"in_review")+COUNTIFS('Features'!$A$3:$A$72,"F-058",'Features'!$G$3:$G$72,"complete")+COUNTIFS('Features'!$A$3:$A$72,"F-058",'Features'!$G$3:$G$72,"in_review")+COUNTIFS('Features'!$A$3:$A$72,"F-060",'Features'!$G$3:$G$72,"complete")+COUNTIFS('Features'!$A$3:$A$72,"F-060",'Features'!$G$3:$G$72,"in_review"))=0,"OPEN — 0 of 10","PARTIAL — "&(COUNTIFS('Features'!$A$3:$A$72,"F-004",'Features'!$G$3:$G$72,"complete")+COUNTIFS('Features'!$A$3:$A$72,"F-004",'Features'!$G$3:$G$72,"in_review")+COUNTIFS('Features'!$A$3:$A$72,"F-005",'Features'!$G$3:$G$72,"complete")+COUNTIFS('Features'!$A$3:$A$72,"F-005",'Features'!$G$3:$G$72,"in_review")+COUNTIFS('Features'!$A$3:$A$72,"F-006",'Features'!$G$3:$G$72,"complete")+COUNTIFS('Features'!$A$3:$A$72,"F-006",'Features'!$G$3:$G$72,"in_review")+COUNTIFS('Features'!$A$3:$A$72,"F-007",'Features'!$G$3:$G$72,"complete")+COUNTIFS('Features'!$A$3:$A$72,"F-007",'Features'!$G$3:$G$72,"in_review")+COUNTIFS('Features'!$A$3:$A$72,"F-008",'Features'!$G$3:$G$72,"complete")+COUNTIFS('Features'!$A$3:$A$72,"F-008",'Features'!$G$3:$G$72,"in_review")+COUNTIFS('Features'!$A$3:$A$72,"F-009",'Features'!$G$3:$G$72,"complete")+COUNTIFS('Features'!$A$3:$A$72,"F-009",'Features'!$G$3:$G$72,"in_review")+COUNTIFS('Features'!$A$3:$A$72,"F-012",'Features'!$G$3:$G$72,"complete")+COUNTIFS('Features'!$A$3:$A$72,"F-012",'Features'!$G$3:$G$72,"in_review")+COUNTIFS('Features'!$A$3:$A$72,"F-022",'Features'!$G$3:$G$72,"complete")+COUNTIFS('Features'!$A$3:$A$72,"F-022",'Features'!$G$3:$G$72,"in_review")+COUNTIFS('Features'!$A$3:$A$72,"F-058",'Features'!$G$3:$G$72,"complete")+COUNTIFS('Features'!$A$3:$A$72,"F-058",'Features'!$G$3:$G$72,"in_review")+COUNTIFS('Features'!$A$3:$A$72,"F-060",'Features'!$G$3:$G$72,"complete")+COUNTIFS('Features'!$A$3:$A$72,"F-060",'Features'!$G$3:$G$72,"in_review"))&" of 10"))) | I5: Core Alpha thesis: Avatar Builder + Forensic Canvas produce a depth of customer understanding generic prompting can't reach. F-022 (Coach mode) extends this in Beta. GEN3 (2026-05-25): = cannot articulate what the customer is actually buying → The Signature (F-060) is the answer; the Decision Trigger (F-058) sharpens it. MVP-critical, validate first. Free tier.
A6: P-002 | B6: I don't know what to ask myself about my customer. | C6: Alpha | D6: Yes | E6: F-001,F-004,F-005,F-006,F-007,F-009,F-060,F-061,F-062 | F6: 9 | G6: =(COUNTIFS('Features'!$A$3:$A$72,"F-001",'Features'!$G$3:$G$72,"complete")+COUNTIFS('Features'!$A$3:$A$72,"F-001",'Features'!$G$3:$G$72,"in_review")+COUNTIFS('Features'!$A$3:$A$72,"F-004",'Features'!$G$3:$G$72,"complete")+COUNTIFS('Features'!$A$3:$A$72,"F-004",'Features'!$G$3:$G$72,"in_review")+COUNTIFS('Features'!$A$3:$A$72,"F-005",'Features'!$G$3:$G$72,"complete")+COUNTIFS('Features'!$A$3:$A$72,"F-005",'Features'!$G$3:$G$72,"in_review")+COUNTIFS('Features'!$A$3:$A$72,"F-006",'Features'!$G$3:$G$72,"complete")+COUNTIFS('Features'!$A$3:$A$72,"F-006",'Features'!$G$3:$G$72,"in_review")+COUNTIFS('Features'!$A$3:$A$72,"F-007",'Features'!$G$3:$G$72,"complete")+COUNTIFS('Features'!$A$3:$A$72,"F-007",'Features'!$G$3:$G$72,"in_review")+COUNTIFS('Features'!$A$3:$A$72,"F-009",'Features'!$G$3:$G$72,"complete")+COUNTIFS('Features'!$A$3:$A$72,"F-009",'Features'!$G$3:$G$72,"in_review")+COUNTIFS('Features'!$A$3:$A$72,"F-060",'Features'!$G$3:$G$72,"complete")+COUNTIFS('Features'!$A$3:$A$72,"F-060",'Features'!$G$3:$G$72,"in_review")+COUNTIFS('Features'!$A$3:$A$72,"F-061",'Features'!$G$3:$G$72,"complete")+COUNTIFS('Features'!$A$3:$A$72,"F-061",'Features'!$G$3:$G$72,"in_review")+COUNTIFS('Features'!$A$3:$A$72,"F-062",'Features'!$G$3:$G$72,"complete")+COUNTIFS('Features'!$A$3:$A$72,"F-062",'Features'!$G$3:$G$72,"in_review")) | H6: =IF((COUNTIFS('Features'!$A$3:$A$72,"F-001",'Features'!$G$3:$G$72,"blocked")+COUNTIFS('Features'!$A$3:$A$72,"F-004",'Features'!$G$3:$G$72,"blocked")+COUNTIFS('Features'!$A$3:$A$72,"F-005",'Features'!$G$3:$G$72,"blocked")+COUNTIFS('Features'!$A$3:$A$72,"F-006",'Features'!$G$3:$G$72,"blocked")+COUNTIFS('Features'!$A$3:$A$72,"F-007",'Features'!$G$3:$G$72,"blocked")+COUNTIFS('Features'!$A$3:$A$72,"F-009",'Features'!$G$3:$G$72,"blocked")+COUNTIFS('Features'!$A$3:$A$72,"F-060",'Features'!$G$3:$G$72,"blocked")+COUNTIFS('Features'!$A$3:$A$72,"F-061",'Features'!$G$3:$G$72,"blocked")+COUNTIFS('Features'!$A$3:$A$72,"F-062",'Features'!$G$3:$G$72,"blocked"))>0,"BLOCKED — see mapped features",IF((COUNTIFS('Features'!$A$3:$A$72,"F-001",'Features'!$G$3:$G$72,"complete")+COUNTIFS('Features'!$A$3:$A$72,"F-001",'Features'!$G$3:$G$72,"in_review")+COUNTIFS('Features'!$A$3:$A$72,"F-004",'Features'!$G$3:$G$72,"complete")+COUNTIFS('Features'!$A$3:$A$72,"F-004",'Features'!$G$3:$G$72,"in_review")+COUNTIFS('Features'!$A$3:$A$72,"F-005",'Features'!$G$3:$G$72,"complete")+COUNTIFS('Features'!$A$3:$A$72,"F-005",'Features'!$G$3:$G$72,"in_review")+COUNTIFS('Features'!$A$3:$A$72,"F-006",'Features'!$G$3:$G$72,"complete")+COUNTIFS('Features'!$A$3:$A$72,"F-006",'Features'!$G$3:$G$72,"in_review")+COUNTIFS('Features'!$A$3:$A$72,"F-007",'Features'!$G$3:$G$72,"complete")+COUNTIFS('Features'!$A$3:$A$72,"F-007",'Features'!$G$3:$G$72,"in_review")+COUNTIFS('Features'!$A$3:$A$72,"F-009",'Features'!$G$3:$G$72,"complete")+COUNTIFS('Features'!$A$3:$A$72,"F-009",'Features'!$G$3:$G$72,"in_review")+COUNTIFS('Features'!$A$3:$A$72,"F-060",'Features'!$G$3:$G$72,"complete")+COUNTIFS('Features'!$A$3:$A$72,"F-060",'Features'!$G$3:$G$72,"in_review")+COUNTIFS('Features'!$A$3:$A$72,"F-061",'Features'!$G$3:$G$72,"complete")+COUNTIFS('Features'!$A$3:$A$72,"F-061",'Features'!$G$3:$G$72,"in_review")+COUNTIFS('Features'!$A$3:$A$72,"F-062",'Features'!$G$3:$G$72,"complete")+COUNTIFS('Features'!$A$3:$A$72,"F-062",'Features'!$G$3:$G$72,"in_review"))=9,"MET",IF((COUNTIFS('Features'!$A$3:$A$72,"F-001",'Features'!$G$3:$G$72,"complete")+COUNTIFS('Features'!$A$3:$A$72,"F-001",'Features'!$G$3:$G$72,"in_review")+COUNTIFS('Features'!$A$3:$A$72,"F-004",'Features'!$G$3:$G$72,"complete")+COUNTIFS('Features'!$A$3:$A$72,"F-004",'Features'!$G$3:$G$72,"in_review")+COUNTIFS('Features'!$A$3:$A$72,"F-005",'Features'!$G$3:$G$72,"complete")+COUNTIFS('Features'!$A$3:$A$72,"F-005",'Features'!$G$3:$G$72,"in_review")+COUNTIFS('Features'!$A$3:$A$72,"F-006",'Features'!$G$3:$G$72,"complete")+COUNTIFS('Features'!$A$3:$A$72,"F-006",'Features'!$G$3:$G$72,"in_review")+COUNTIFS('Features'!$A$3:$A$72,"F-007",'Features'!$G$3:$G$72,"complete")+COUNTIFS('Features'!$A$3:$A$72,"F-007",'Features'!$G$3:$G$72,"in_review")+COUNTIFS('Features'!$A$3:$A$72,"F-009",'Features'!$G$3:$G$72,"complete")+COUNTIFS('Features'!$A$3:$A$72,"F-009",'Features'!$G$3:$G$72,"in_review")+COUNTIFS('Features'!$A$3:$A$72,"F-060",'Features'!$G$3:$G$72,"complete")+COUNTIFS('Features'!$A$3:$A$72,"F-060",'Features'!$G$3:$G$72,"in_review")+COUNTIFS('Features'!$A$3:$A$72,"F-061",'Features'!$G$3:$G$72,"complete")+COUNTIFS('Features'!$A$3:$A$72,"F-061",'Features'!$G$3:$G$72,"in_review")+COUNTIFS('Features'!$A$3:$A$72,"F-062",'Features'!$G$3:$G$72,"complete")+COUNTIFS('Features'!$A$3:$A$72,"F-062",'Features'!$G$3:$G$72,"in_review"))=0,"OPEN — 0 of 9","PARTIAL — "&(COUNTIFS('Features'!$A$3:$A$72,"F-001",'Features'!$G$3:$G$72,"complete")+COUNTIFS('Features'!$A$3:$A$72,"F-001",'Features'!$G$3:$G$72,"in_review")+COUNTIFS('Features'!$A$3:$A$72,"F-004",'Features'!$G$3:$G$72,"complete")+COUNTIFS('Features'!$A$3:$A$72,"F-004",'Features'!$G$3:$G$72,"in_review")+COUNTIFS('Features'!$A$3:$A$72,"F-005",'Features'!$G$3:$G$72,"complete")+COUNTIFS('Features'!$A$3:$A$72,"F-005",'Features'!$G$3:$G$72,"in_review")+COUNTIFS('Features'!$A$3:$A$72,"F-006",'Features'!$G$3:$G$72,"complete")+COUNTIFS('Features'!$A$3:$A$72,"F-006",'Features'!$G$3:$G$72,"in_review")+COUNTIFS('Features'!$A$3:$A$72,"F-007",'Features'!$G$3:$G$72,"complete")+COUNTIFS('Features'!$A$3:$A$72,"F-007",'Features'!$G$3:$G$72,"in_review")+COUNTIFS('Features'!$A$3:$A$72,"F-009",'Features'!$G$3:$G$72,"complete")+COUNTIFS('Features'!$A$3:$A$72,"F-009",'Features'!$G$3:$G$72,"in_review")+COUNTIFS('Features'!$A$3:$A$72,"F-060",'Features'!$G$3:$G$72,"complete")+COUNTIFS('Features'!$A$3:$A$72,"F-060",'Features'!$G$3:$G$72,"in_review")+COUNTIFS('Features'!$A$3:$A$72,"F-061",'Features'!$G$3:$G$72,"complete")+COUNTIFS('Features'!$A$3:$A$72,"F-061",'Features'!$G$3:$G$72,"in_review")+COUNTIFS('Features'!$A$3:$A$72,"F-062",'Features'!$G$3:$G$72,"complete")+COUNTIFS('Features'!$A$3:$A$72,"F-062",'Features'!$G$3:$G$72,"in_review"))&" of 9"))) | I6: 10-Q conversation + 4 Avatar Builder sections provide the inquiry structure. F-009 'Think About This' mode explicitly generates reflective questions per field.
A7: P-003 | B7: My brand strategy doc is shallow or doesn't exist. | C7: Alpha | D7: Partial | E7: F-003,F-008,F-023,F-053 | F7: 4 | G7: =(COUNTIFS('Features'!$A$3:$A$72,"F-003",'Features'!$G$3:$G$72,"complete")+COUNTIFS('Features'!$A$3:$A$72,"F-003",'Features'!$G$3:$G$72,"in_review")+COUNTIFS('Features'!$A$3:$A$72,"F-008",'Features'!$G$3:$G$72,"complete")+COUNTIFS('Features'!$A$3:$A$72,"F-008",'Features'!$G$3:$G$72,"in_review")+COUNTIFS('Features'!$A$3:$A$72,"F-023",'Features'!$G$3:$G$72,"complete")+COUNTIFS('Features'!$A$3:$A$72,"F-023",'Features'!$G$3:$G$72,"in_review")+COUNTIFS('Features'!$A$3:$A$72,"F-053",'Features'!$G$3:$G$72,"complete")+COUNTIFS('Features'!$A$3:$A$72,"F-053",'Features'!$G$3:$G$72,"in_review")) | H7: =IF((COUNTIFS('Features'!$A$3:$A$72,"F-003",'Features'!$G$3:$G$72,"blocked")+COUNTIFS('Features'!$A$3:$A$72,"F-008",'Features'!$G$3:$G$72,"blocked")+COUNTIFS('Features'!$A$3:$A$72,"F-023",'Features'!$G$3:$G$72,"blocked")+COUNTIFS('Features'!$A$3:$A$72,"F-053",'Features'!$G$3:$G$72,"blocked"))>0,"BLOCKED — see mapped features",IF((COUNTIFS('Features'!$A$3:$A$72,"F-003",'Features'!$G$3:$G$72,"complete")+COUNTIFS('Features'!$A$3:$A$72,"F-003",'Features'!$G$3:$G$72,"in_review")+COUNTIFS('Features'!$A$3:$A$72,"F-008",'Features'!$G$3:$G$72,"complete")+COUNTIFS('Features'!$A$3:$A$72,"F-008",'Features'!$G$3:$G$72,"in_review")+COUNTIFS('Features'!$A$3:$A$72,"F-023",'Features'!$G$3:$G$72,"complete")+COUNTIFS('Features'!$A$3:$A$72,"F-023",'Features'!$G$3:$G$72,"in_review")+COUNTIFS('Features'!$A$3:$A$72,"F-053",'Features'!$G$3:$G$72,"complete")+COUNTIFS('Features'!$A$3:$A$72,"F-053",'Features'!$G$3:$G$72,"in_review"))=4,"MET",IF((COUNTIFS('Features'!$A$3:$A$72,"F-003",'Features'!$G$3:$G$72,"complete")+COUNTIFS('Features'!$A$3:$A$72,"F-003",'Features'!$G$3:$G$72,"in_review")+COUNTIFS('Features'!$A$3:$A$72,"F-008",'Features'!$G$3:$G$72,"complete")+COUNTIFS('Features'!$A$3:$A$72,"F-008",'Features'!$G$3:$G$72,"in_review")+COUNTIFS('Features'!$A$3:$A$72,"F-023",'Features'!$G$3:$G$72,"complete")+COUNTIFS('Features'!$A$3:$A$72,"F-023",'Features'!$G$3:$G$72,"in_review")+COUNTIFS('Features'!$A$3:$A$72,"F-053",'Features'!$G$3:$G$72,"complete")+COUNTIFS('Features'!$A$3:$A$72,"F-053",'Features'!$G$3:$G$72,"in_review"))=0,"OPEN — 0 of 4","PARTIAL — "&(COUNTIFS('Features'!$A$3:$A$72,"F-003",'Features'!$G$3:$G$72,"complete")+COUNTIFS('Features'!$A$3:$A$72,"F-003",'Features'!$G$3:$G$72,"in_review")+COUNTIFS('Features'!$A$3:$A$72,"F-008",'Features'!$G$3:$G$72,"complete")+COUNTIFS('Features'!$A$3:$A$72,"F-008",'Features'!$G$3:$G$72,"in_review")+COUNTIFS('Features'!$A$3:$A$72,"F-023",'Features'!$G$3:$G$72,"complete")+COUNTIFS('Features'!$A$3:$A$72,"F-023",'Features'!$G$3:$G$72,"in_review")+COUNTIFS('Features'!$A$3:$A$72,"F-053",'Features'!$G$3:$G$72,"complete")+COUNTIFS('Features'!$A$3:$A$72,"F-053",'Features'!$G$3:$G$72,"in_review"))&" of 4"))) | I7: F-008 (Forensic Canvas via generate-brand-strategy-document) is the primary fulfilment — substantially shipped. Polished Word export (F-023) and multi-angle (F-053) are Beta extensions.
A8: P-004 | B8: My copy and creative aren't grounded in strategy. | C8: Beta | D8: No | E8: F-008,F-020,F-021,F-055 | F8: 4 | G8: =(COUNTIFS('Features'!$A$3:$A$72,"F-008",'Features'!$G$3:$G$72,"complete")+COUNTIFS('Features'!$A$3:$A$72,"F-008",'Features'!$G$3:$G$72,"in_review")+COUNTIFS('Features'!$A$3:$A$72,"F-020",'Features'!$G$3:$G$72,"complete")+COUNTIFS('Features'!$A$3:$A$72,"F-020",'Features'!$G$3:$G$72,"in_review")+COUNTIFS('Features'!$A$3:$A$72,"F-021",'Features'!$G$3:$G$72,"complete")+COUNTIFS('Features'!$A$3:$A$72,"F-021",'Features'!$G$3:$G$72,"in_review")+COUNTIFS('Features'!$A$3:$A$72,"F-055",'Features'!$G$3:$G$72,"complete")+COUNTIFS('Features'!$A$3:$A$72,"F-055",'Features'!$G$3:$G$72,"in_review")) | H8: =IF((COUNTIFS('Features'!$A$3:$A$72,"F-008",'Features'!$G$3:$G$72,"blocked")+COUNTIFS('Features'!$A$3:$A$72,"F-020",'Features'!$G$3:$G$72,"blocked")+COUNTIFS('Features'!$A$3:$A$72,"F-021",'Features'!$G$3:$G$72,"blocked")+COUNTIFS('Features'!$A$3:$A$72,"F-055",'Features'!$G$3:$G$72,"blocked"))>0,"BLOCKED — see mapped features",IF((COUNTIFS('Features'!$A$3:$A$72,"F-008",'Features'!$G$3:$G$72,"complete")+COUNTIFS('Features'!$A$3:$A$72,"F-008",'Features'!$G$3:$G$72,"in_review")+COUNTIFS('Features'!$A$3:$A$72,"F-020",'Features'!$G$3:$G$72,"complete")+COUNTIFS('Features'!$A$3:$A$72,"F-020",'Features'!$G$3:$G$72,"in_review")+COUNTIFS('Features'!$A$3:$A$72,"F-021",'Features'!$G$3:$G$72,"complete")+COUNTIFS('Features'!$A$3:$A$72,"F-021",'Features'!$G$3:$G$72,"in_review")+COUNTIFS('Features'!$A$3:$A$72,"F-055",'Features'!$G$3:$G$72,"complete")+COUNTIFS('Features'!$A$3:$A$72,"F-055",'Features'!$G$3:$G$72,"in_review"))=4,"MET",IF((COUNTIFS('Features'!$A$3:$A$72,"F-008",'Features'!$G$3:$G$72,"complete")+COUNTIFS('Features'!$A$3:$A$72,"F-008",'Features'!$G$3:$G$72,"in_review")+COUNTIFS('Features'!$A$3:$A$72,"F-020",'Features'!$G$3:$G$72,"complete")+COUNTIFS('Features'!$A$3:$A$72,"F-020",'Features'!$G$3:$G$72,"in_review")+COUNTIFS('Features'!$A$3:$A$72,"F-021",'Features'!$G$3:$G$72,"complete")+COUNTIFS('Features'!$A$3:$A$72,"F-021",'Features'!$G$3:$G$72,"in_review")+COUNTIFS('Features'!$A$3:$A$72,"F-055",'Features'!$G$3:$G$72,"complete")+COUNTIFS('Features'!$A$3:$A$72,"F-055",'Features'!$G$3:$G$72,"in_review"))=0,"OPEN — 0 of 4","PARTIAL — "&(COUNTIFS('Features'!$A$3:$A$72,"F-008",'Features'!$G$3:$G$72,"complete")+COUNTIFS('Features'!$A$3:$A$72,"F-008",'Features'!$G$3:$G$72,"in_review")+COUNTIFS('Features'!$A$3:$A$72,"F-020",'Features'!$G$3:$G$72,"complete")+COUNTIFS('Features'!$A$3:$A$72,"F-020",'Features'!$G$3:$G$72,"in_review")+COUNTIFS('Features'!$A$3:$A$72,"F-021",'Features'!$G$3:$G$72,"complete")+COUNTIFS('Features'!$A$3:$A$72,"F-021",'Features'!$G$3:$G$72,"in_review")+COUNTIFS('Features'!$A$3:$A$72,"F-055",'Features'!$G$3:$G$72,"complete")+COUNTIFS('Features'!$A$3:$A$72,"F-055",'Features'!$G$3:$G$72,"in_review"))&" of 4"))) | I8: Requires Create mode outputs (F-020 Amazon, F-021 Voice Guide, F-055 Design brief). None ship in Alpha. The canvas (F-008) is the anchor but not the deliverable for this problem.
A9: P-005 | B9: My customer's actual language doesn't make it into my copy. | C9: Beta | D9: Partial | E9: F-007,F-008,F-020,F-021,F-063 | F9: 5 | G9: =(COUNTIFS('Features'!$A$3:$A$72,"F-007",'Features'!$G$3:$G$72,"complete")+COUNTIFS('Features'!$A$3:$A$72,"F-007",'Features'!$G$3:$G$72,"in_review")+COUNTIFS('Features'!$A$3:$A$72,"F-008",'Features'!$G$3:$G$72,"complete")+COUNTIFS('Features'!$A$3:$A$72,"F-008",'Features'!$G$3:$G$72,"in_review")+COUNTIFS('Features'!$A$3:$A$72,"F-020",'Features'!$G$3:$G$72,"complete")+COUNTIFS('Features'!$A$3:$A$72,"F-020",'Features'!$G$3:$G$72,"in_review")+COUNTIFS('Features'!$A$3:$A$72,"F-021",'Features'!$G$3:$G$72,"complete")+COUNTIFS('Features'!$A$3:$A$72,"F-021",'Features'!$G$3:$G$72,"in_review")+COUNTIFS('Features'!$A$3:$A$72,"F-063",'Features'!$G$3:$G$72,"complete")+COUNTIFS('Features'!$A$3:$A$72,"F-063",'Features'!$G$3:$G$72,"in_review")) | H9: =IF((COUNTIFS('Features'!$A$3:$A$72,"F-007",'Features'!$G$3:$G$72,"blocked")+COUNTIFS('Features'!$A$3:$A$72,"F-008",'Features'!$G$3:$G$72,"blocked")+COUNTIFS('Features'!$A$3:$A$72,"F-020",'Features'!$G$3:$G$72,"blocked")+COUNTIFS('Features'!$A$3:$A$72,"F-021",'Features'!$G$3:$G$72,"blocked")+COUNTIFS('Features'!$A$3:$A$72,"F-063",'Features'!$G$3:$G$72,"blocked"))>0,"BLOCKED — see mapped features",IF((COUNTIFS('Features'!$A$3:$A$72,"F-007",'Features'!$G$3:$G$72,"complete")+COUNTIFS('Features'!$A$3:$A$72,"F-007",'Features'!$G$3:$G$72,"in_review")+COUNTIFS('Features'!$A$3:$A$72,"F-008",'Features'!$G$3:$G$72,"complete")+COUNTIFS('Features'!$A$3:$A$72,"F-008",'Features'!$G$3:$G$72,"in_review")+COUNTIFS('Features'!$A$3:$A$72,"F-020",'Features'!$G$3:$G$72,"complete")+COUNTIFS('Features'!$A$3:$A$72,"F-020",'Features'!$G$3:$G$72,"in_review")+COUNTIFS('Features'!$A$3:$A$72,"F-021",'Features'!$G$3:$G$72,"complete")+COUNTIFS('Features'!$A$3:$A$72,"F-021",'Features'!$G$3:$G$72,"in_review")+COUNTIFS('Features'!$A$3:$A$72,"F-063",'Features'!$G$3:$G$72,"complete")+COUNTIFS('Features'!$A$3:$A$72,"F-063",'Features'!$G$3:$G$72,"in_review"))=5,"MET",IF((COUNTIFS('Features'!$A$3:$A$72,"F-007",'Features'!$G$3:$G$72,"complete")+COUNTIFS('Features'!$A$3:$A$72,"F-007",'Features'!$G$3:$G$72,"in_review")+COUNTIFS('Features'!$A$3:$A$72,"F-008",'Features'!$G$3:$G$72,"complete")+COUNTIFS('Features'!$A$3:$A$72,"F-008",'Features'!$G$3:$G$72,"in_review")+COUNTIFS('Features'!$A$3:$A$72,"F-020",'Features'!$G$3:$G$72,"complete")+COUNTIFS('Features'!$A$3:$A$72,"F-020",'Features'!$G$3:$G$72,"in_review")+COUNTIFS('Features'!$A$3:$A$72,"F-021",'Features'!$G$3:$G$72,"complete")+COUNTIFS('Features'!$A$3:$A$72,"F-021",'Features'!$G$3:$G$72,"in_review")+COUNTIFS('Features'!$A$3:$A$72,"F-063",'Features'!$G$3:$G$72,"complete")+COUNTIFS('Features'!$A$3:$A$72,"F-063",'Features'!$G$3:$G$72,"in_review"))=0,"OPEN — 0 of 5","PARTIAL — "&(COUNTIFS('Features'!$A$3:$A$72,"F-007",'Features'!$G$3:$G$72,"complete")+COUNTIFS('Features'!$A$3:$A$72,"F-007",'Features'!$G$3:$G$72,"in_review")+COUNTIFS('Features'!$A$3:$A$72,"F-008",'Features'!$G$3:$G$72,"complete")+COUNTIFS('Features'!$A$3:$A$72,"F-008",'Features'!$G$3:$G$72,"in_review")+COUNTIFS('Features'!$A$3:$A$72,"F-020",'Features'!$G$3:$G$72,"complete")+COUNTIFS('Features'!$A$3:$A$72,"F-020",'Features'!$G$3:$G$72,"in_review")+COUNTIFS('Features'!$A$3:$A$72,"F-021",'Features'!$G$3:$G$72,"complete")+COUNTIFS('Features'!$A$3:$A$72,"F-021",'Features'!$G$3:$G$72,"in_review")+COUNTIFS('Features'!$A$3:$A$72,"F-063",'Features'!$G$3:$G$72,"complete")+COUNTIFS('Features'!$A$3:$A$72,"F-063",'Features'!$G$3:$G$72,"in_review"))&" of 5"))) | I9: F-007 Voice of Customer extracts verbatim language in Alpha. F-020/F-021 (Beta) consume it. Alpha can prove 'we capture the language'; only Beta proves 'it shows up in your copy'.
A10: P-006 | B10: My existing image/video set is doing something — but I can't tell what's missing or off. | C10: GA | D10: No | E10: F-006,F-007,F-054,F-055 | F10: 4 | G10: =(COUNTIFS('Features'!$A$3:$A$72,"F-006",'Features'!$G$3:$G$72,"complete")+COUNTIFS('Features'!$A$3:$A$72,"F-006",'Features'!$G$3:$G$72,"in_review")+COUNTIFS('Features'!$A$3:$A$72,"F-007",'Features'!$G$3:$G$72,"complete")+COUNTIFS('Features'!$A$3:$A$72,"F-007",'Features'!$G$3:$G$72,"in_review")+COUNTIFS('Features'!$A$3:$A$72,"F-054",'Features'!$G$3:$G$72,"complete")+COUNTIFS('Features'!$A$3:$A$72,"F-054",'Features'!$G$3:$G$72,"in_review")+COUNTIFS('Features'!$A$3:$A$72,"F-055",'Features'!$G$3:$G$72,"complete")+COUNTIFS('Features'!$A$3:$A$72,"F-055",'Features'!$G$3:$G$72,"in_review")) | H10: =IF((COUNTIFS('Features'!$A$3:$A$72,"F-006",'Features'!$G$3:$G$72,"blocked")+COUNTIFS('Features'!$A$3:$A$72,"F-007",'Features'!$G$3:$G$72,"blocked")+COUNTIFS('Features'!$A$3:$A$72,"F-054",'Features'!$G$3:$G$72,"blocked")+COUNTIFS('Features'!$A$3:$A$72,"F-055",'Features'!$G$3:$G$72,"blocked"))>0,"BLOCKED — see mapped features",IF((COUNTIFS('Features'!$A$3:$A$72,"F-006",'Features'!$G$3:$G$72,"complete")+COUNTIFS('Features'!$A$3:$A$72,"F-006",'Features'!$G$3:$G$72,"in_review")+COUNTIFS('Features'!$A$3:$A$72,"F-007",'Features'!$G$3:$G$72,"complete")+COUNTIFS('Features'!$A$3:$A$72,"F-007",'Features'!$G$3:$G$72,"in_review")+COUNTIFS('Features'!$A$3:$A$72,"F-054",'Features'!$G$3:$G$72,"complete")+COUNTIFS('Features'!$A$3:$A$72,"F-054",'Features'!$G$3:$G$72,"in_review")+COUNTIFS('Features'!$A$3:$A$72,"F-055",'Features'!$G$3:$G$72,"complete")+COUNTIFS('Features'!$A$3:$A$72,"F-055",'Features'!$G$3:$G$72,"in_review"))=4,"MET",IF((COUNTIFS('Features'!$A$3:$A$72,"F-006",'Features'!$G$3:$G$72,"complete")+COUNTIFS('Features'!$A$3:$A$72,"F-006",'Features'!$G$3:$G$72,"in_review")+COUNTIFS('Features'!$A$3:$A$72,"F-007",'Features'!$G$3:$G$72,"complete")+COUNTIFS('Features'!$A$3:$A$72,"F-007",'Features'!$G$3:$G$72,"in_review")+COUNTIFS('Features'!$A$3:$A$72,"F-054",'Features'!$G$3:$G$72,"complete")+COUNTIFS('Features'!$A$3:$A$72,"F-054",'Features'!$G$3:$G$72,"in_review")+COUNTIFS('Features'!$A$3:$A$72,"F-055",'Features'!$G$3:$G$72,"complete")+COUNTIFS('Features'!$A$3:$A$72,"F-055",'Features'!$G$3:$G$72,"in_review"))=0,"OPEN — 0 of 4","PARTIAL — "&(COUNTIFS('Features'!$A$3:$A$72,"F-006",'Features'!$G$3:$G$72,"complete")+COUNTIFS('Features'!$A$3:$A$72,"F-006",'Features'!$G$3:$G$72,"in_review")+COUNTIFS('Features'!$A$3:$A$72,"F-007",'Features'!$G$3:$G$72,"complete")+COUNTIFS('Features'!$A$3:$A$72,"F-007",'Features'!$G$3:$G$72,"in_review")+COUNTIFS('Features'!$A$3:$A$72,"F-054",'Features'!$G$3:$G$72,"complete")+COUNTIFS('Features'!$A$3:$A$72,"F-054",'Features'!$G$3:$G$72,"in_review")+COUNTIFS('Features'!$A$3:$A$72,"F-055",'Features'!$G$3:$G$72,"complete")+COUNTIFS('Features'!$A$3:$A$72,"F-055",'Features'!$G$3:$G$72,"in_review"))&" of 4"))) | I10: InfinityVault's specific need (N-002). F-054 is conditional on the asset-tracking decision gate. F-006/F-007 supply the 'what should this connect to' context.
A11: P-007 | B11: I have no thinking partner who remembers my brand. | C11: Beta | D11: No | E11: F-022,F-031,F-049 | F11: 3 | G11: =(COUNTIFS('Features'!$A$3:$A$72,"F-022",'Features'!$G$3:$G$72,"complete")+COUNTIFS('Features'!$A$3:$A$72,"F-022",'Features'!$G$3:$G$72,"in_review")+COUNTIFS('Features'!$A$3:$A$72,"F-031",'Features'!$G$3:$G$72,"complete")+COUNTIFS('Features'!$A$3:$A$72,"F-031",'Features'!$G$3:$G$72,"in_review")+COUNTIFS('Features'!$A$3:$A$72,"F-049",'Features'!$G$3:$G$72,"complete")+COUNTIFS('Features'!$A$3:$A$72,"F-049",'Features'!$G$3:$G$72,"in_review")) | H11: =IF((COUNTIFS('Features'!$A$3:$A$72,"F-022",'Features'!$G$3:$G$72,"blocked")+COUNTIFS('Features'!$A$3:$A$72,"F-031",'Features'!$G$3:$G$72,"blocked")+COUNTIFS('Features'!$A$3:$A$72,"F-049",'Features'!$G$3:$G$72,"blocked"))>0,"BLOCKED — see mapped features",IF((COUNTIFS('Features'!$A$3:$A$72,"F-022",'Features'!$G$3:$G$72,"complete")+COUNTIFS('Features'!$A$3:$A$72,"F-022",'Features'!$G$3:$G$72,"in_review")+COUNTIFS('Features'!$A$3:$A$72,"F-031",'Features'!$G$3:$G$72,"complete")+COUNTIFS('Features'!$A$3:$A$72,"F-031",'Features'!$G$3:$G$72,"in_review")+COUNTIFS('Features'!$A$3:$A$72,"F-049",'Features'!$G$3:$G$72,"complete")+COUNTIFS('Features'!$A$3:$A$72,"F-049",'Features'!$G$3:$G$72,"in_review"))=3,"MET",IF((COUNTIFS('Features'!$A$3:$A$72,"F-022",'Features'!$G$3:$G$72,"complete")+COUNTIFS('Features'!$A$3:$A$72,"F-022",'Features'!$G$3:$G$72,"in_review")+COUNTIFS('Features'!$A$3:$A$72,"F-031",'Features'!$G$3:$G$72,"complete")+COUNTIFS('Features'!$A$3:$A$72,"F-031",'Features'!$G$3:$G$72,"in_review")+COUNTIFS('Features'!$A$3:$A$72,"F-049",'Features'!$G$3:$G$72,"complete")+COUNTIFS('Features'!$A$3:$A$72,"F-049",'Features'!$G$3:$G$72,"in_review"))=0,"OPEN — 0 of 3","PARTIAL — "&(COUNTIFS('Features'!$A$3:$A$72,"F-022",'Features'!$G$3:$G$72,"complete")+COUNTIFS('Features'!$A$3:$A$72,"F-022",'Features'!$G$3:$G$72,"in_review")+COUNTIFS('Features'!$A$3:$A$72,"F-031",'Features'!$G$3:$G$72,"complete")+COUNTIFS('Features'!$A$3:$A$72,"F-031",'Features'!$G$3:$G$72,"in_review")+COUNTIFS('Features'!$A$3:$A$72,"F-049",'Features'!$G$3:$G$72,"complete")+COUNTIFS('Features'!$A$3:$A$72,"F-049",'Features'!$G$3:$G$72,"in_review"))&" of 3"))) | I11: F-022 Coach mode is the answer. RAG (F-049) makes the memory queryable. F-031 (My Brands) lets the partner know which brand we're discussing.
A12: P-008 | B12: I can't cheaply test multiple positioning angles. | C12: Beta | D12: No | E12: F-042,F-053,F-055 | F12: 3 | G12: =(COUNTIFS('Features'!$A$3:$A$72,"F-042",'Features'!$G$3:$G$72,"complete")+COUNTIFS('Features'!$A$3:$A$72,"F-042",'Features'!$G$3:$G$72,"in_review")+COUNTIFS('Features'!$A$3:$A$72,"F-053",'Features'!$G$3:$G$72,"complete")+COUNTIFS('Features'!$A$3:$A$72,"F-053",'Features'!$G$3:$G$72,"in_review")+COUNTIFS('Features'!$A$3:$A$72,"F-055",'Features'!$G$3:$G$72,"complete")+COUNTIFS('Features'!$A$3:$A$72,"F-055",'Features'!$G$3:$G$72,"in_review")) | H12: =IF((COUNTIFS('Features'!$A$3:$A$72,"F-042",'Features'!$G$3:$G$72,"blocked")+COUNTIFS('Features'!$A$3:$A$72,"F-053",'Features'!$G$3:$G$72,"blocked")+COUNTIFS('Features'!$A$3:$A$72,"F-055",'Features'!$G$3:$G$72,"blocked"))>0,"BLOCKED — see mapped features",IF((COUNTIFS('Features'!$A$3:$A$72,"F-042",'Features'!$G$3:$G$72,"complete")+COUNTIFS('Features'!$A$3:$A$72,"F-042",'Features'!$G$3:$G$72,"in_review")+COUNTIFS('Features'!$A$3:$A$72,"F-053",'Features'!$G$3:$G$72,"complete")+COUNTIFS('Features'!$A$3:$A$72,"F-053",'Features'!$G$3:$G$72,"in_review")+COUNTIFS('Features'!$A$3:$A$72,"F-055",'Features'!$G$3:$G$72,"complete")+COUNTIFS('Features'!$A$3:$A$72,"F-055",'Features'!$G$3:$G$72,"in_review"))=3,"MET",IF((COUNTIFS('Features'!$A$3:$A$72,"F-042",'Features'!$G$3:$G$72,"complete")+COUNTIFS('Features'!$A$3:$A$72,"F-042",'Features'!$G$3:$G$72,"in_review")+COUNTIFS('Features'!$A$3:$A$72,"F-053",'Features'!$G$3:$G$72,"complete")+COUNTIFS('Features'!$A$3:$A$72,"F-053",'Features'!$G$3:$G$72,"in_review")+COUNTIFS('Features'!$A$3:$A$72,"F-055",'Features'!$G$3:$G$72,"complete")+COUNTIFS('Features'!$A$3:$A$72,"F-055",'Features'!$G$3:$G$72,"in_review"))=0,"OPEN — 0 of 3","PARTIAL — "&(COUNTIFS('Features'!$A$3:$A$72,"F-042",'Features'!$G$3:$G$72,"complete")+COUNTIFS('Features'!$A$3:$A$72,"F-042",'Features'!$G$3:$G$72,"in_review")+COUNTIFS('Features'!$A$3:$A$72,"F-053",'Features'!$G$3:$G$72,"complete")+COUNTIFS('Features'!$A$3:$A$72,"F-053",'Features'!$G$3:$G$72,"in_review")+COUNTIFS('Features'!$A$3:$A$72,"F-055",'Features'!$G$3:$G$72,"complete")+COUNTIFS('Features'!$A$3:$A$72,"F-055",'Features'!$G$3:$G$72,"in_review"))&" of 3"))) | I12: F-053 is the primary fulfilment. F-055 lets each angle drive its own design brief. F-042 comparison view (GA) lets the user A/B them.
A13: P-009 | B13: I can't tell when my strategy and my live assets have drifted apart. | C13: GA | D13: No | E13: F-028,F-029,F-030,F-043,F-054 | F13: 5 | G13: =(COUNTIFS('Features'!$A$3:$A$72,"F-028",'Features'!$G$3:$G$72,"complete")+COUNTIFS('Features'!$A$3:$A$72,"F-028",'Features'!$G$3:$G$72,"in_review")+COUNTIFS('Features'!$A$3:$A$72,"F-029",'Features'!$G$3:$G$72,"complete")+COUNTIFS('Features'!$A$3:$A$72,"F-029",'Features'!$G$3:$G$72,"in_review")+COUNTIFS('Features'!$A$3:$A$72,"F-030",'Features'!$G$3:$G$72,"complete")+COUNTIFS('Features'!$A$3:$A$72,"F-030",'Features'!$G$3:$G$72,"in_review")+COUNTIFS('Features'!$A$3:$A$72,"F-043",'Features'!$G$3:$G$72,"complete")+COUNTIFS('Features'!$A$3:$A$72,"F-043",'Features'!$G$3:$G$72,"in_review")+COUNTIFS('Features'!$A$3:$A$72,"F-054",'Features'!$G$3:$G$72,"complete")+COUNTIFS('Features'!$A$3:$A$72,"F-054",'Features'!$G$3:$G$72,"in_review")) | H13: =IF((COUNTIFS('Features'!$A$3:$A$72,"F-028",'Features'!$G$3:$G$72,"blocked")+COUNTIFS('Features'!$A$3:$A$72,"F-029",'Features'!$G$3:$G$72,"blocked")+COUNTIFS('Features'!$A$3:$A$72,"F-030",'Features'!$G$3:$G$72,"blocked")+COUNTIFS('Features'!$A$3:$A$72,"F-043",'Features'!$G$3:$G$72,"blocked")+COUNTIFS('Features'!$A$3:$A$72,"F-054",'Features'!$G$3:$G$72,"blocked"))>0,"BLOCKED — see mapped features",IF((COUNTIFS('Features'!$A$3:$A$72,"F-028",'Features'!$G$3:$G$72,"complete")+COUNTIFS('Features'!$A$3:$A$72,"F-028",'Features'!$G$3:$G$72,"in_review")+COUNTIFS('Features'!$A$3:$A$72,"F-029",'Features'!$G$3:$G$72,"complete")+COUNTIFS('Features'!$A$3:$A$72,"F-029",'Features'!$G$3:$G$72,"in_review")+COUNTIFS('Features'!$A$3:$A$72,"F-030",'Features'!$G$3:$G$72,"complete")+COUNTIFS('Features'!$A$3:$A$72,"F-030",'Features'!$G$3:$G$72,"in_review")+COUNTIFS('Features'!$A$3:$A$72,"F-043",'Features'!$G$3:$G$72,"complete")+COUNTIFS('Features'!$A$3:$A$72,"F-043",'Features'!$G$3:$G$72,"in_review")+COUNTIFS('Features'!$A$3:$A$72,"F-054",'Features'!$G$3:$G$72,"complete")+COUNTIFS('Features'!$A$3:$A$72,"F-054",'Features'!$G$3:$G$72,"in_review"))=5,"MET",IF((COUNTIFS('Features'!$A$3:$A$72,"F-028",'Features'!$G$3:$G$72,"complete")+COUNTIFS('Features'!$A$3:$A$72,"F-028",'Features'!$G$3:$G$72,"in_review")+COUNTIFS('Features'!$A$3:$A$72,"F-029",'Features'!$G$3:$G$72,"complete")+COUNTIFS('Features'!$A$3:$A$72,"F-029",'Features'!$G$3:$G$72,"in_review")+COUNTIFS('Features'!$A$3:$A$72,"F-030",'Features'!$G$3:$G$72,"complete")+COUNTIFS('Features'!$A$3:$A$72,"F-030",'Features'!$G$3:$G$72,"in_review")+COUNTIFS('Features'!$A$3:$A$72,"F-043",'Features'!$G$3:$G$72,"complete")+COUNTIFS('Features'!$A$3:$A$72,"F-043",'Features'!$G$3:$G$72,"in_review")+COUNTIFS('Features'!$A$3:$A$72,"F-054",'Features'!$G$3:$G$72,"complete")+COUNTIFS('Features'!$A$3:$A$72,"F-054",'Features'!$G$3:$G$72,"in_review"))=0,"OPEN — 0 of 5","PARTIAL — "&(COUNTIFS('Features'!$A$3:$A$72,"F-028",'Features'!$G$3:$G$72,"complete")+COUNTIFS('Features'!$A$3:$A$72,"F-028",'Features'!$G$3:$G$72,"in_review")+COUNTIFS('Features'!$A$3:$A$72,"F-029",'Features'!$G$3:$G$72,"complete")+COUNTIFS('Features'!$A$3:$A$72,"F-029",'Features'!$G$3:$G$72,"in_review")+COUNTIFS('Features'!$A$3:$A$72,"F-030",'Features'!$G$3:$G$72,"complete")+COUNTIFS('Features'!$A$3:$A$72,"F-030",'Features'!$G$3:$G$72,"in_review")+COUNTIFS('Features'!$A$3:$A$72,"F-043",'Features'!$G$3:$G$72,"complete")+COUNTIFS('Features'!$A$3:$A$72,"F-043",'Features'!$G$3:$G$72,"in_review")+COUNTIFS('Features'!$A$3:$A$72,"F-054",'Features'!$G$3:$G$72,"complete")+COUNTIFS('Features'!$A$3:$A$72,"F-054",'Features'!$G$3:$G$72,"in_review"))&" of 5"))) | I13: Conditional on the asset-tracking decision. F-043 field edit history adds the temporal dimension on the strategy side.
A14: P-010 | B14: Every marketing decision feels reactive. | C14: GA | D14: No | E14: F-008,F-022,F-038,F-053 | F14: 4 | G14: =(COUNTIFS('Features'!$A$3:$A$72,"F-008",'Features'!$G$3:$G$72,"complete")+COUNTIFS('Features'!$A$3:$A$72,"F-008",'Features'!$G$3:$G$72,"in_review")+COUNTIFS('Features'!$A$3:$A$72,"F-022",'Features'!$G$3:$G$72,"complete")+COUNTIFS('Features'!$A$3:$A$72,"F-022",'Features'!$G$3:$G$72,"in_review")+COUNTIFS('Features'!$A$3:$A$72,"F-038",'Features'!$G$3:$G$72,"complete")+COUNTIFS('Features'!$A$3:$A$72,"F-038",'Features'!$G$3:$G$72,"in_review")+COUNTIFS('Features'!$A$3:$A$72,"F-053",'Features'!$G$3:$G$72,"complete")+COUNTIFS('Features'!$A$3:$A$72,"F-053",'Features'!$G$3:$G$72,"in_review")) | H14: =IF((COUNTIFS('Features'!$A$3:$A$72,"F-008",'Features'!$G$3:$G$72,"blocked")+COUNTIFS('Features'!$A$3:$A$72,"F-022",'Features'!$G$3:$G$72,"blocked")+COUNTIFS('Features'!$A$3:$A$72,"F-038",'Features'!$G$3:$G$72,"blocked")+COUNTIFS('Features'!$A$3:$A$72,"F-053",'Features'!$G$3:$G$72,"blocked"))>0,"BLOCKED — see mapped features",IF((COUNTIFS('Features'!$A$3:$A$72,"F-008",'Features'!$G$3:$G$72,"complete")+COUNTIFS('Features'!$A$3:$A$72,"F-008",'Features'!$G$3:$G$72,"in_review")+COUNTIFS('Features'!$A$3:$A$72,"F-022",'Features'!$G$3:$G$72,"complete")+COUNTIFS('Features'!$A$3:$A$72,"F-022",'Features'!$G$3:$G$72,"in_review")+COUNTIFS('Features'!$A$3:$A$72,"F-038",'Features'!$G$3:$G$72,"complete")+COUNTIFS('Features'!$A$3:$A$72,"F-038",'Features'!$G$3:$G$72,"in_review")+COUNTIFS('Features'!$A$3:$A$72,"F-053",'Features'!$G$3:$G$72,"complete")+COUNTIFS('Features'!$A$3:$A$72,"F-053",'Features'!$G$3:$G$72,"in_review"))=4,"MET",IF((COUNTIFS('Features'!$A$3:$A$72,"F-008",'Features'!$G$3:$G$72,"complete")+COUNTIFS('Features'!$A$3:$A$72,"F-008",'Features'!$G$3:$G$72,"in_review")+COUNTIFS('Features'!$A$3:$A$72,"F-022",'Features'!$G$3:$G$72,"complete")+COUNTIFS('Features'!$A$3:$A$72,"F-022",'Features'!$G$3:$G$72,"in_review")+COUNTIFS('Features'!$A$3:$A$72,"F-038",'Features'!$G$3:$G$72,"complete")+COUNTIFS('Features'!$A$3:$A$72,"F-038",'Features'!$G$3:$G$72,"in_review")+COUNTIFS('Features'!$A$3:$A$72,"F-053",'Features'!$G$3:$G$72,"complete")+COUNTIFS('Features'!$A$3:$A$72,"F-053",'Features'!$G$3:$G$72,"in_review"))=0,"OPEN — 0 of 4","PARTIAL — "&(COUNTIFS('Features'!$A$3:$A$72,"F-008",'Features'!$G$3:$G$72,"complete")+COUNTIFS('Features'!$A$3:$A$72,"F-008",'Features'!$G$3:$G$72,"in_review")+COUNTIFS('Features'!$A$3:$A$72,"F-022",'Features'!$G$3:$G$72,"complete")+COUNTIFS('Features'!$A$3:$A$72,"F-022",'Features'!$G$3:$G$72,"in_review")+COUNTIFS('Features'!$A$3:$A$72,"F-038",'Features'!$G$3:$G$72,"complete")+COUNTIFS('Features'!$A$3:$A$72,"F-038",'Features'!$G$3:$G$72,"in_review")+COUNTIFS('Features'!$A$3:$A$72,"F-053",'Features'!$G$3:$G$72,"complete")+COUNTIFS('Features'!$A$3:$A$72,"F-053",'Features'!$G$3:$G$72,"in_review"))&" of 4"))) | I14: Forensic Canvas as North Star (F-008), Coach for ongoing decisions (F-022), performance metrics (F-038) close the loop. F-053 lets decisions live at the angle level.
A15: P-011 | B15: I don't know where my brand is failing. | C15: Alpha | D15: Yes | E15: F-057,F-059,F-027 | F15: 3 | G15: =(COUNTIFS('Features'!$A$3:$A$72,"F-057",'Features'!$G$3:$G$72,"complete")+COUNTIFS('Features'!$A$3:$A$72,"F-057",'Features'!$G$3:$G$72,"in_review")+COUNTIFS('Features'!$A$3:$A$72,"F-059",'Features'!$G$3:$G$72,"complete")+COUNTIFS('Features'!$A$3:$A$72,"F-059",'Features'!$G$3:$G$72,"in_review")+COUNTIFS('Features'!$A$3:$A$72,"F-027",'Features'!$G$3:$G$72,"complete")+COUNTIFS('Features'!$A$3:$A$72,"F-027",'Features'!$G$3:$G$72,"in_review")) | H15: =IF((COUNTIFS('Features'!$A$3:$A$72,"F-057",'Features'!$G$3:$G$72,"blocked")+COUNTIFS('Features'!$A$3:$A$72,"F-059",'Features'!$G$3:$G$72,"blocked")+COUNTIFS('Features'!$A$3:$A$72,"F-027",'Features'!$G$3:$G$72,"blocked"))>0,"BLOCKED — see mapped features",IF((COUNTIFS('Features'!$A$3:$A$72,"F-057",'Features'!$G$3:$G$72,"complete")+COUNTIFS('Features'!$A$3:$A$72,"F-057",'Features'!$G$3:$G$72,"in_review")+COUNTIFS('Features'!$A$3:$A$72,"F-059",'Features'!$G$3:$G$72,"complete")+COUNTIFS('Features'!$A$3:$A$72,"F-059",'Features'!$G$3:$G$72,"in_review")+COUNTIFS('Features'!$A$3:$A$72,"F-027",'Features'!$G$3:$G$72,"complete")+COUNTIFS('Features'!$A$3:$A$72,"F-027",'Features'!$G$3:$G$72,"in_review"))=3,"MET",IF((COUNTIFS('Features'!$A$3:$A$72,"F-057",'Features'!$G$3:$G$72,"complete")+COUNTIFS('Features'!$A$3:$A$72,"F-057",'Features'!$G$3:$G$72,"in_review")+COUNTIFS('Features'!$A$3:$A$72,"F-059",'Features'!$G$3:$G$72,"complete")+COUNTIFS('Features'!$A$3:$A$72,"F-059",'Features'!$G$3:$G$72,"in_review")+COUNTIFS('Features'!$A$3:$A$72,"F-027",'Features'!$G$3:$G$72,"complete")+COUNTIFS('Features'!$A$3:$A$72,"F-027",'Features'!$G$3:$G$72,"in_review"))=0,"OPEN — 0 of 3","PARTIAL — "&(COUNTIFS('Features'!$A$3:$A$72,"F-057",'Features'!$G$3:$G$72,"complete")+COUNTIFS('Features'!$A$3:$A$72,"F-057",'Features'!$G$3:$G$72,"in_review")+COUNTIFS('Features'!$A$3:$A$72,"F-059",'Features'!$G$3:$G$72,"complete")+COUNTIFS('Features'!$A$3:$A$72,"F-059",'Features'!$G$3:$G$72,"in_review")+COUNTIFS('Features'!$A$3:$A$72,"F-027",'Features'!$G$3:$G$72,"complete")+COUNTIFS('Features'!$A$3:$A$72,"F-027",'Features'!$G$3:$G$72,"in_review"))&" of 3"))) | I15: GEN3 (2026-05-25): Trevor's problem #3/#9 — the Trust Gap™ Score (F-057) names the gap (insight / positioning / empathy / authenticity) and the bridge (F-059) turns it into momentum. MVP-critical: this is the hook, validate FIRST [Analysis 2026-05-17]. Free tier.
A16: P-012 | B16: Brand strategy expertise is inaccessible at my price point. | C16: Beta | D16: No | E16: F-019,F-064 | F16: 2 | G16: =(COUNTIFS('Features'!$A$3:$A$72,"F-019",'Features'!$G$3:$G$72,"complete")+COUNTIFS('Features'!$A$3:$A$72,"F-019",'Features'!$G$3:$G$72,"in_review")+COUNTIFS('Features'!$A$3:$A$72,"F-064",'Features'!$G$3:$G$72,"complete")+COUNTIFS('Features'!$A$3:$A$72,"F-064",'Features'!$G$3:$G$72,"in_review")) | H16: =IF((COUNTIFS('Features'!$A$3:$A$72,"F-019",'Features'!$G$3:$G$72,"blocked")+COUNTIFS('Features'!$A$3:$A$72,"F-064",'Features'!$G$3:$G$72,"blocked"))>0,"BLOCKED — see mapped features",IF((COUNTIFS('Features'!$A$3:$A$72,"F-019",'Features'!$G$3:$G$72,"complete")+COUNTIFS('Features'!$A$3:$A$72,"F-019",'Features'!$G$3:$G$72,"in_review")+COUNTIFS('Features'!$A$3:$A$72,"F-064",'Features'!$G$3:$G$72,"complete")+COUNTIFS('Features'!$A$3:$A$72,"F-064",'Features'!$G$3:$G$72,"in_review"))=2,"MET",IF((COUNTIFS('Features'!$A$3:$A$72,"F-019",'Features'!$G$3:$G$72,"complete")+COUNTIFS('Features'!$A$3:$A$72,"F-019",'Features'!$G$3:$G$72,"in_review")+COUNTIFS('Features'!$A$3:$A$72,"F-064",'Features'!$G$3:$G$72,"complete")+COUNTIFS('Features'!$A$3:$A$72,"F-064",'Features'!$G$3:$G$72,"in_review"))=0,"OPEN — 0 of 2","PARTIAL — "&(COUNTIFS('Features'!$A$3:$A$72,"F-019",'Features'!$G$3:$G$72,"complete")+COUNTIFS('Features'!$A$3:$A$72,"F-019",'Features'!$G$3:$G$72,"in_review")+COUNTIFS('Features'!$A$3:$A$72,"F-064",'Features'!$G$3:$G$72,"complete")+COUNTIFS('Features'!$A$3:$A$72,"F-064",'Features'!$G$3:$G$72,"in_review"))&" of 2"))) | I16: GEN3 (2026-05-25): Trevor's problem #7 — a brand strategist costs £3k–£15k; the freemium app (F-019) delivers structured brand thinking at £29/mo, with locked-but-visible fields (F-064) enticing upgrade. Paid tier.

Sheet Features
A1: Features — implementation status by launch phase
A2: feature_id | B2: feature_name | C2: area | D2: description | E2: phase_required | F2: priority | G2: status | H2: percent_complete | I2: blocker | J2: owner | K2: depends_on | L2: problems_addressed | M2: effort_estimate_hours | N2: actual_hours | O2: notes | P2: last_updated
A3: F-001 | B3: Layer 1 conversation engine | C3: conversation | D3: 10-question Layer 1 flow with Trevor-voice fallback responses and real-time canvas-sidebar updates. | E3: Alpha | F3: P0 | G3: in_progress | H3: 35 | J3: Matthew | K3: F-018 | L3: P-002 | M3: 40 | N3: 0 | O3: AUDIT 2026-05-16: Trevor persona prompt + free-form Claude streaming exist; the *10-question script* and per-question off-topic fallbacks DO NOT (F-001.1/F-001.2). Streaming + persistence are solid. Mobile keyboard handling minimal. | P3: 46167
A4: F-002 | B4: Canvas sidebar real-time population | C4: canvas | D4: Canvas sidebar updates as Layer 1 conversation progresses, showing extracted fields with confidence indicators. | E4: Alpha | F4: P0 | G4: in_progress | H4: 65 | J4: Matthew | K4: F-001,F-012 | M4: 20 | N4: 0 | O4: AUDIT 2026-05-16: Field-extraction → sidebar pipeline is mature (F-002.1, 80%). Quality badges render BUT use value heuristics (fieldQualityScore) not extractor confidence — acceptance criterion not literally met (F-002.2 reduced from 100→75). Mobile sheet works but state not persisted (F-002.3). | P4: 46167
A5: F-003 | B5: Draft Canvas synthesis | C5: canvas | D5: Synthesise Layer 1 inputs into a coherent Draft Canvas with DRAFT badge and clear Forensic upgrade prompt. | E5: Alpha | F5: P0 | G5: in_progress | H5: 14 | J5: Matthew | K5: F-001,F-018 | L5: P-003 | M5: 24 | N5: 0 | O5: AUDIT 2026-05-16: Tier distinction is conceptual only — zero structural code hits for 'DRAFT'/'tier'. Synthesis with Trevor voice exists (generate-brand-strategy-section + voice.ts) but generates the full doc, not a Draft subset. DRAFT badge and Forensic upgrade CTA both 0%. | P5: 46167
A6: F-004 | B6: Avatar Builder — Psychographic Profile | C6: avatar_builder | D6: Section 1 of the four-section Avatar Builder. Captures values, identity, worldview. | E6: Alpha | F6: P0 | G6: in_progress | H6: 62 | J6: Matthew | K6: F-003,F-009 | L6: P-001,P-002 | M6: 32 | N6: 0 | O6: AUDIT 2026-05-16: V2 chapter UI delivers progressive disclosure + persistence well, but field schema flattens Gen 3 psychographic dimensions into coarse textareas (F-004.1 60%). 3 of 4 AI modes present; FieldChatButton missing from V2 (F-004.3 35%). Completion gate logic exists but button not mounted in render tree (F-004.5 55%). RECONCILE (2026-05-25): maps into the new 5-stage conversational flow ending in The Signature (F-060); guided dialogue, not a 4-section form [F 144128256 @04:26]. 5-stage structure pending Trevor/Matthew sign-off. | P6: 46167
A7: F-005 | B7: Avatar Builder — Buying Behaviour | C7: avatar_builder | D7: Section 2. Captures purchase triggers, objections, decision criteria, channels. | E7: Alpha | F7: P0 | G7: in_progress | H7: 55 | J7: Matthew | K7: F-004 | L7: P-001,P-002 | M7: 32 | N7: 0 | O7: AUDIT 2026-05-16: V2 chapter map has no dedicated 'Buying Behaviour' chapter — closest is BUYER_INTENT which is conceptually different. V1 AvatarBuilder has the right tab. Data shape exists; UI split V1↔V2. RECONCILE (2026-05-25): maps into the new 5-stage conversational flow ending in The Signature (F-060); guided dialogue, not a 4-section form [F 144128256 @04:26]. 5-stage structure pending Trevor/Matthew sign-off. | P7: 46167
A8: F-006 | B8: Avatar Builder — Emotional Journey Mapping | C8: avatar_builder | D8: Section 3. Pre/during/post purchase emotional states; The Decision Trigger™ originates here (captured standalone in F-058). | E8: Alpha | F8: P0 | G8: in_progress | H8: 43 | J8: Matthew | K8: F-005 | L8: P-001,P-002,P-006 | M8: 36 | N8: 0 | O8: AUDIT 2026-05-16: Emotional fields exist (EMOTIONAL_CONNECTION + CUSTOMER_EXPERIENCE chapters) but Gen 3 Emotional Journey framing absent; Trigger Moment field with elevated visual treatment (F-006.2) is the most prominent miss — zero hits in codebase. RECONCILE (2026-05-25): maps into the new 5-stage conversational flow ending in The Signature (F-060); guided dialogue, not a 4-section form [F 144128256 @04:26]. 5-stage structure pending Trevor/Matthew sign-off. | P8: 46167
A9: F-007 | B9: Avatar Builder — Voice of Customer | C9: avatar_builder | D9: Section 4. Paste-in reviews and testimonials; extract verbatim language for copy hooks. | E9: Alpha | F9: P0 | G9: in_progress | H9: 30 | J9: Matthew | K9: F-006 | L9: P-001,P-002,P-005,P-006 | M9: 40 | N9: 0 | O9: AUDIT 2026-05-16: Review intake is URL/ASIN-driven via ReviewAnalyzerModal (scrape model), not Gen 3 paste-raw-reviews model. voice-of-customer-analysis edge function DOES NOT EXIST. V1 analysis is fully mocked. Use/discard phrase cards (F-007.3) ~10%. RECONCILE (2026-05-25): maps into the new 5-stage conversational flow ending in The Signature (F-060); guided dialogue, not a 4-section form [F 144128256 @04:26]. 5-stage structure pending Trevor/Matthew sign-off. | P9: 46167
A10: F-008 | B10: Forensic Canvas synthesis | C10: canvas | D10: 28+ field canvas synthesised from Avatar Builder, auto-populating from Avatar data partially in real time; strategy doc generable at any point (no forced step-gating). The Decision Trigger™ displayed prominently. | E10: Alpha | F10: P0 | G10: in_progress | H10: 39 | J10: Matthew | K10: F-004,F-005,F-006,F-007 | L10: P-001,P-003,P-004,P-005,P-010 | M10: 40 | N10: 0 | O10: AUDIT 2026-05-16: 35-field schema exists (exceeds 28+) and Markdown export pipeline is mature, but Forensic *tier* differentiation does NOT exist — single unified synthesis path. Trigger Moment 'Strategic Entry Point' callout (F-008.3) and Draft↔Forensic toggle (F-008.4) both 0%. Rollup dropped from 80→39%: the doc ships, but the criteria asking for tier-specific behaviour are unmet. GEN3 (2026-05-25): canvas auto-populates from Avatar data (partially real-time); no forced step-gating; 'Trigger Moment' renamed The Decision Trigger™ (also captured standalone in F-058) [F 144128256 @27:00,@31:00]. | P10: 46167
A11: F-009 | B11: AI Assistance system | C11: avatar_builder | D11: Four modes — Think About This, Real-World Examples, Get AI Suggestions, Get AI Auto-Populate — available per field. | E11: Alpha | F11: P0 | G11: in_progress | H11: 19 | J11: Matthew | K11: F-018 | L11: P-001,P-002 | M11: 48 | N11: 0 | O11: AUDIT 2026-05-16: Only ONE AI mode is independently invocable — a single 'Generate with AI' button per field (AIButton.tsx). 'Think About This' and 'Real-World Examples' modes don't exist; 'Auto-Populate' is delivered implicitly via chat extraction + ghost text. No 4-mode selector UI. Rollup dropped from 30→19%. GEN3 (2026-05-25): MVP ships static example text for avatar/Before-State prompts; AI-suggestion path deferred and paid-tier when built [F 144128256 @11:42-12:52]. | P11: 46167
A12: F-010 | B12: Progressive disclosure UI | C12: design_system | D12: Avatar Builder fields reveal progressively to avoid form fatigue; mobile-first. | E12: Alpha | F12: P0 | G12: not_started | H12: 2 | J12: Matthew | M12: 24 | N12: 0 | O12: AUDIT 2026-05-16: shadcn Accordion used informally for chapter disclosure; no documented disclosure pattern, no mobile-first audit committed. Rollup dropped from 25→3%. | P12: 46167
A13: F-011 | B13: Manual edit lock | C13: avatar_builder | D13: Fields manually edited by the user are flagged and never silently overwritten by AI suggestions. | E13: Alpha | F13: P0 | G13: in_progress | H13: 57 | J13: Matthew | M13: 12 | N13: 0 | O13: AUDIT 2026-05-16: field_source ('ai'|'manual') exists and survives reload BUT is not the same as a 'manuallyEdited' boolean — system pairs it with separate is_locked user-toggle. AI overwrite guard works only for *explicitly locked* fields (F-011.2 65%), not for manually edited unlocked ones. F-011.1 reduced from 100→70% in_review. | P13: 46167
A14: F-012 | B14: Field extraction pipeline with confidence scoring | C14: infrastructure | D14: Conversation inputs → structured field extraction with per-field confidence score. Drives the quality badges. | E14: Alpha | F14: P0 | G14: in_progress | H14: 45 | J14: Matthew | L14: P-001 | M14: 32 | N14: 0 | O14: AUDIT 2026-05-16: Edge function returns confidence scores (F-012.1 85%), but no confidence→badge mapping is implemented (F-012.2 was 100% wrongly — now 50%). Two unrelated badge systems coexist (heuristic on sidebar, percentage on chat). | P14: 46167
A15: F-013 | B15: Feedback Moment 1 — Entry signal modal | C15: feedback_loop | D15: Modal after Draft Canvas asks whether the conversation revealed new territory; routes to feedback sheet. | E15: Alpha | F15: P0 | G15: not_started | H15: 0 | J15: Matthew | K15: F-003,F-017 | M15: 12 | N15: 0 | O15: AUDIT 2026-05-16: Nothing exists. BrandCanvas page has no first-view detection, no modal, no 'entry signal' question copy, no moment-tagged write path. Greenfield build needed. | P15: 46167
A16: F-014 | B16: Feedback Moment 2 — Use intent inline panel | C16: feedback_loop | D16: Inline panel after Forensic Canvas asks what the user intends to do with it (and surfaces asset-update demand signal). | E16: Alpha | F16: P0 | G16: not_started | H16: 0 | J16: Matthew | K16: F-008,F-017 | M16: 12 | N16: 0 | O16: AUDIT 2026-05-16: Nothing exists. No inline panel, no 'use intent' multi-select, no 'update existing assets' option (which drives the asset-tracking gate), no moment-2 write path. Greenfield build needed. | P16: 46167
A17: F-015 | B17: Feedback Moment 3 — 14-day async email | C17: feedback_loop | D17: Day-14 email asks what the user has actually done with the canvas and what's missing. | E17: Alpha | F17: P0 | G17: not_started | H17: 0 | J17: Matthew | K17: F-017 | M17: 8 | N17: 0 | O17: AUDIT 2026-05-16: Nothing exists. No scheduled-send infrastructure (pg_cron not enabled, no day-offset queue), no 14-day email template, no inbound reply parsing. Resend exists only for synchronous send-framework-email (different feature). Greenfield build needed. | P17: 46167
A18: F-016 | B18: Feedback response sheet integration | C18: infrastructure | D18: All three feedback moments write to a single sheet (Google Sheets or Supabase view) Matthew can monitor daily. | E18: Alpha | F18: P0 | G18: not_started | H18: 0 | J18: Matthew | M18: 8 | N18: 0 | O18: AUDIT 2026-05-16: Existing beta_feedback table is wide-form (overall_rating/liked_most/improvements/issues) — wrong shape for moment-tagged events. Need new feedback_events table with (moment, user_id, timestamp, payload JSONB). Existing BetaFeedback infrastructure will NOT compose — treat as separate older system; build moment infra fresh. | P18: 46167
A19: F-017 | B19: Error monitoring | C19: infrastructure | D19: Sentry (or equivalent) capturing client + edge function errors. Daily review during alpha. | E19: Alpha | F19: P0 | G19: not_started | H19: 0 | J19: Matthew | M19: 6 | N19: 0 | O19: AUDIT 2026-05-16: Nothing exists. No Sentry/Rollbar/Bugsnag/LogRocket/Datadog in package.json. ErrorBoundary.tsx only console.errors with a commented placeholder. No source-map upload, no CI workflows directory. Greenfield install. | P19: 46167
A20: F-018 | B20: Tester onboarding flow | C20: accounts | D20: One-page Loom + in-app welcome that frames alpha state and the three feedback moments. | E20: Alpha | F20: P0 | G20: in_progress | H20: 13 | J20: Matthew | M20: 8 | N20: 0 | O20: AUDIT 2026-05-16: BetaWelcome page exists at /beta but is a self-serve registration form gated by localStorage — not auto-shown on first login, doesn't name Trevor or framework, not dismissable. StartHere has a Vimeo intro (not Loom). No invitation template, no 'first 10'/'7-day'/'30-min debrief' language. Resend not configured for invitations. | P20: 46167
A21: F-019 | B21: Pay gate (freemium) | C21: pay_gate | D21: Freemium model. Free = core tools + The Signature + limited AI; paid (£29/mo; one-off £67 notional/TBD) unlocks AI-heavy features (Review Lab analysis, unlimited prompts/iterations). Stripe + post-payment action menu. | E21: Beta | F21: P0 | G21: not_started | H21: 0 | J21: Matthew | K21: F-008 | L21: P-012 | M21: 40 | N21: 0 | O21: Central conversion test of beta. Pay-gate previews must use real canvas data. GEN3 (2026-05-25): reframed from two pricing tiers to freemium; canvas fields locked-but-visible for non-subscribers (F-064) [F 144128256 @32:26-34:29]. | P21: 46167
A22: F-020 | B22: Create mode — Amazon listing copy | C22: create_mode | D22: Generate Amazon listing copy from Forensic Canvas using Trevor-voice prompts. | E22: Beta | F22: P0 | G22: not_started | H22: 0 | J22: Matthew | K22: F-008,F-019 | L22: P-004,P-005 | M22: 32 | N22: 0 | O22: First Create-mode output. Anchors the pay-gate preview. | P22: 46167
A23: F-021 | B23: Create mode — Brand Voice Guide | C23: create_mode | D23: Generate Brand Voice Guide document from Forensic Canvas. | E23: Beta | F23: P0 | G23: not_started | H23: 0 | J23: Matthew | K23: F-008,F-019 | L23: P-004,P-005 | M23: 24 | N23: 0 | P23: 46167
A24: F-022 | B24: Coach mode v1 | C24: coach_mode | D24: Open conversation with full canvas context and document upload support. | E24: Beta | F24: P0 | G24: not_started | H24: 0 | J24: Matthew | K24: F-008 | L24: P-001,P-007,P-010 | M24: 56 | N24: 0 | O24: Required to deliver the £29/mo subscription value prop per Trevor's spec. GEN3 (2026-05-25): Coach auto-briefed on Diagnostic + Avatar data — no manual re-paste (fixes Gen-1 CX) [F 144128256 @34:29]. | P24: 46167
A25: F-023 | B25: Export — PDF and Word | C25: export | D25: PDF and Word exports of both Draft and Forensic canvases. | E25: Beta | F25: P0 | G25: in_progress | H25: 65 | J25: Matthew | K25: F-003,F-008 | L25: P-003 | M25: 24 | N25: 0 | O25: PDF + Markdown shipped: BrandCanvasPDFExport, MarkdownPDFExporter, BrandMarkdownExport, generate-brand-strategy-pdf edge function. Word (.docx) export is the remaining gap. Once Draft/Forensic tier split lands in F-003/F-008, ensure both tiers export. | P25: 46167
A26: F-024 | B26: Analytics + funnel tracking | C26: analytics | D26: PostHog or Mixpanel events on every funnel step; cohort analysis enabled. | E26: Beta | F26: P0 | G26: not_started | H26: 0 | J26: Matthew | M26: 16 | N26: 0 | O26: Conversion data is the whole point of beta. | P26: 46167
A27: F-025 | B27: Support workflow | C27: infrastructure | D27: Intercom (or email) inbox with documented SLA; paying users get answers. | E27: Beta | F27: P0 | G27: not_started | H27: 0 | J27: Matthew | M27: 8 | N27: 0 | O27: Refund-rate risk is partly a support-responsiveness problem. | P27: 46167
A28: F-026 | B28: ROI testimonial harvest email sequence | C28: feedback_loop | D28: Day-0, day-14, day-30, day-60 emails plus debrief invite when results report positive. | E28: Beta | F28: P0 | G28: not_started | H28: 0 | J28: Matthew | K28: F-015 | M28: 12 | N28: 0 | O28: Target: 5+ verified testimonials by end of Beta; 10+ within 3 months. | P28: 46167
A29: F-027 | B29: Brand Diagnostic integration | C29: conversation | D29: Diagnostic CTA dynamic (Brand Coach vs strategist) + score handoff into Layer 1 + visual identity refresh. | E29: Beta | F29: P0 | G29: in_progress | H29: 70 | J29: Matthew | L29: P-011 | M29: 20 | N29: 0 | O29: Diagnostic largely exists (FreeDiagnostic + BetaFeedback components). Handoff into Layer 1 still loose. GEN3 (2026-05-25): feeds the Trust Gap™ Score (F-057); beta signup capture writes to the same DB [F 140678453 @16:26]. | P29: 46167
A30: F-028 | B30: Asset Inventory v1 | C30: asset_tracking | D30: User can add assets, tag type (listing/email/social/ad/landing/product/other), mark alignment status manually. | E30: Beta | F30: P1 | G30: not_started | H30: 0 | I30: Conditional on Alpha decision gate | J30: Matthew | K30: F-014 | L30: P-009 | M30: 40 | N30: 0 | O30: DEFERRED DECISION. Gate at end of Alpha. Default is NO. Trevor's Gen 3 spec does not include asset tracking — only ship if Moment 2 signal is ≥40%. | P30: 46167
A31: F-029 | B31: Asset Inventory v1.5 — Canvas linkage | C31: asset_tracking | D31: Mark asset as aligned to a specific canvas version; later canvas updates flag asset as stale. | E31: Beta | F31: P1 | G31: not_started | H31: 0 | I31: Conditional on F-028 | J31: Matthew | K31: F-028 | L31: P-009 | M31: 32 | N31: 0 | O31: Introduces the temporal signal — user can see what's out of date. | P31: 46167
A32: F-030 | B32: Asset Inventory v2 — Diff surface | C32: asset_tracking | D32: When canvas changes, show user a list of likely-affected assets with diff reason (Trigger Moment changed, voice changed, etc.). | E32: GA | F32: P1 | G32: not_started | H32: 0 | I32: Conditional on F-029 | J32: Matthew | K32: F-029 | L32: P-009 | M32: 56 | N32: 0 | O32: Likely a GA-era feature per brief; listed for completeness. | P32: 46167
A33: F-031 | B33: My Brands dashboard | C33: accounts | D33: Multi-brand dashboard with brand switcher; users can manage 2+ brands. | E33: GA | F33: P0 | G33: not_started | H33: 0 | J33: Matthew | K33: F-046 | L33: P-007 | M33: 40 | N33: 0 | O33: Power users will have multiple brands; product caps out at one customer without this. | P33: 46167
A34: F-032 | B34: Anonymous-to-authenticated migration | C34: accounts | D34: Diagnostic completers without accounts have their data preserved on signup. | E34: GA | F34: P0 | G34: not_started | H34: 0 | J34: Matthew | K34: F-027 | M34: 16 | N34: 0 | O34: Top-of-funnel users drop off without this. | P34: 46167
A35: F-033 | B35: Self-serve onboarding tour | C35: design_system | D35: Tooltip-light onboarding tour; no human needed to start. | E35: GA | F35: P0 | G35: not_started | H35: 0 | J35: Matthew | M35: 16 | N35: 0 | O35: Public launch means support cost scales with users — self-serve protects margin. | P35: 46167
A36: F-034 | B36: Pricing page (cold-traffic optimised) | C36: pay_gate | D36: Standalone pricing page that converts cold traffic; A/B tested in late beta. | E36: GA | F36: P0 | G36: not_started | H36: 0 | J36: Matthew | K36: F-019 | M36: 16 | N36: 0 | O36: Conversion surface for non-warm visitors. | P36: 46167
A37: F-035 | B37: Status page | C37: infrastructure | D37: Public uptime page + incident communication channel. | E37: GA | F37: P0 | G37: not_started | H37: 0 | J37: Matthew | M37: 8 | N37: 0 | O37: Trust signal required for paid users. | P37: 46167
A38: F-036 | B38: Knowledge base | C38: infrastructure | D38: 10–20 articles seeded from Beta support tickets covering common questions. | E38: GA | F38: P0 | G38: not_started | H38: 0 | J38: Matthew | K38: F-025 | M38: 24 | N38: 0 | O38: Reduces ticket volume and improves time-to-value. | P38: 46167
A39: F-037 | B39: Refund policy + ToS + Privacy Policy | C39: infrastructure | D39: Standard SaaS refund (14-day), Terms of Service, Privacy Policy. | E39: GA | F39: P0 | G39: not_started | H39: 0 | J39: Matthew | M39: 8 | N39: 0 | O39: Legal hygiene required for paid public product. | P39: 46167
A40: F-038 | B40: Performance metrics tracking | C40: analytics | D40: Per-avatar manual entry of ROAS, CTR, CPA, conversion rate, custom metrics. Drives ROI testimonials. | E40: GA | F40: P0 | G40: not_started | H40: 0 | J40: Matthew | K40: F-046 | L40: P-010 | M40: 32 | N40: 0 | O40: OPEN QUESTION: existing V2 PRD scopes this as a P0 V2 feature. Trevor's Gen 3 spec does not address it. Treated here as GA P0; needs Matthew sign-off. | P40: 46167
A41: F-039 | B41: Referral programme | C41: infrastructure | D41: In-product referral mechanism with 20% rev share. | E41: GA | F41: P1 | G41: not_started | H41: 0 | J41: Matthew | K41: F-019 | M41: 24 | N41: 0 | O41: Acquisition lever from GA Plan. | P41: 46167
A42: F-040 | B42: Affiliate tracking infrastructure | C42: infrastructure | D42: Partner affiliate links, attribution, payout reporting. | E42: GA | F42: P1 | G42: not_started | H42: 0 | J42: Matthew | M42: 24 | N42: 0 | O42: Brand strategist partner channel needs attribution before outreach. | P42: 46167
A43: F-041 | B43: SEO foundation | C43: infrastructure | D43: Sitemap, schema markup, content templates for long-tail brand strategy queries. | E43: GA | F43: P1 | G43: not_started | H43: 0 | J43: Matthew | M43: 20 | N43: 0 | O43: Three-month organic ramp — start at beginning of beta to earn GA traffic. | P43: 46167
A44: F-042 | B44: Avatar comparison view | C44: avatar_builder | D44: Side-by-side comparison of two avatars (different segments, different brands). | E44: GA | F44: P1 | G44: not_started | H44: 0 | J44: Matthew | K44: F-031 | L44: P-008 | M44: 24 | N44: 0 | O44: Power-user feature; rewards multi-canvas usage. | P44: 46167
A45: F-043 | B45: Field edit history viewer | C45: avatar_builder | D45: Audit log per field showing edit history and which canvas version each value was active in. | E45: GA | F45: P1 | G45: not_started | H45: 0 | J45: Matthew | K45: F-046 | L45: P-009 | M45: 16 | N45: 0 | O45: Schema needs field_edit_history table. | P45: 46167
A46: F-044 | B46: Bulk operations | C46: avatar_builder | D46: Copy fields between avatars; find/replace across an avatar. | E46: GA | F46: P1 | G46: not_started | H46: 0 | J46: Matthew | K46: F-031 | M46: 20 | N46: 0 | O46: Power-user feature. | P46: 46167
A47: F-045a | B47: TikTok-specific landing page | C47: design_system | D47: Variant landing page optimised for TikTok cold traffic. | E47: Post-GA | F47: P1 | G47: not_started | H47: 0 | J47: Matthew | K47: F-034 | M47: 12 | N47: 0 | O47: TikTok integration is GA+4wks per Launch Roadmap; not a build dependency. | P47: 46167
A48: F-045b | B48: UTM tagging across TikTok touchpoints | C48: analytics | D48: Consistent UTM scheme on every TikTok-originating link. | E48: Post-GA | F48: P1 | G48: not_started | H48: 0 | J48: Matthew | K48: F-024 | M48: 4 | N48: 0 | P48: 46167
A49: F-045c | B49: TikTok Pixel integration | C49: analytics | D49: TikTok Pixel installed on landing pages and conversion events. | E49: Post-GA | F49: P1 | G49: not_started | H49: 0 | J49: Matthew | M49: 4 | N49: 0 | P49: 46167
A50: F-045d | B50: Self-report attribution question on signup | C50: analytics | D50: 'Where did you hear about us?' on signup; option for TikTok and named creators. | E50: Post-GA | F50: P1 | G50: not_started | H50: 0 | J50: Matthew | M50: 4 | N50: 0 | O50: Pairs with UTM data to triangulate true attribution. | P50: 46167
A51: F-046 | B51: Database migrations (additive) | C51: infrastructure | D51: Migrations for brands, avatars, avatar_profiles, brand_strategies, performance_metrics, field_edit_history, assets (if asset tracking ships). | E51: Alpha | F51: P0 | G51: in_progress | H51: 50 | J51: Matthew | M51: 24 | N51: 0 | O51: Additive only. RLS policies in F-047. | P51: 46167
A52: F-047 | B52: RLS policies for new tables | C52: infrastructure | D52: Row-level-security policies on every new table created in F-046. | E52: Alpha | F52: P0 | G52: in_progress | H52: 40 | J52: Matthew | K52: F-046 | M52: 12 | N52: 0 | P52: 46167
A53: F-048 | B53: Edge functions | C53: infrastructure | D53: conversation, canvas-synthesis, create-copy, coach-conversation, voice-of-customer-analysis edge functions. | E53: Alpha | F53: P0 | G53: in_progress | H53: 40 | J53: Matthew | M53: 40 | N53: 0 | O53: idea-framework-consultant exists; Gen 3 functions partially overlap. Audit needed. | P53: 46167
A54: F-049 | B54: RAG integration with System KB | C54: infrastructure | D54: Retrieval from the existing System KB vector store (vs_6948707b318c81918a90e9b44970a99e) in all relevant edge functions. | E54: Alpha | F54: P0 | G54: in_progress | H54: 60 | J54: Matthew | K54: F-048 | L54: P-007 | M54: 16 | N54: 0 | O54: OpenAI embeddings removed in commit 260128b (consolidated to Claude/internal embeddings) — verify RAG pipeline still wired. | P54: 46167
A55: F-050 | B55: Feature flag system | C55: infrastructure | D55: Ensure useFeatureFlag gates every V2/Gen 3 route; flags toggle independently. | E55: Alpha | F55: P0 | G55: in_progress | H55: 80 | J55: Matthew | M55: 8 | N55: 0 | O55: Hook already exists. Audit V2 routes for missing gates. | P55: 46167
A56: F-051 | B56: Pre-implementation refactoring sprint | C56: infrastructure | D56: Week-0 refactoring sprint per V2 PRD: service extraction, field sync architecture, component composition. | E56: Alpha | F56: P0 | G56: in_progress | H56: 70 | J56: Matthew | M56: 40 | N56: 0 | O56: Refactor patterns shipped (SupabaseChatService split, FieldSyncService, AIAssistant decomposition). Verify all Gen 3 work picks up new patterns. | P56: 46167
A57: F-053 | B57: Multiple positioning angles per avatar | C57: avatar_builder | D57: Support multiple positioning / marketing angle variants for the same avatar — each angle has its own brand strategy doc / canvas section, but shares the underlying avatar. | E57: Beta | F57: P1 | G57: not_started | H57: 0 | J57: Matthew | K57: F-008,F-031 | L57: P-003,P-008,P-010 | M57: 40 | N57: 0 | O57: Validates A/B angle testing for paying users. Each angle = a strategy variant tied to a canonical avatar. Surfaces in Coach mode and Export. OPEN: schema choice — separate canvases per angle vs angle-tagged sections within one canvas. | P57: 46167
A58: F-054 | B58: Image asset side-by-side comparison and tracking | C58: asset_tracking | D58: Upload current image/video assets, view side-by-side, tag against avatar + angle, flag gaps and emotional-connection opportunities. | E58: GA | F58: P1 | G58: not_started | H58: 0 | I58: Conditional on F-028 (asset tracking decision) | J58: Matthew | K58: F-028,F-053 | L58: P-006,P-009 | M58: 56 | N58: 0 | O58: Extension of asset_tracking that goes beyond text. Anchored to InfinityVault need N-002 (assess images/videos, identify what's missing, surface emotional-connection opportunities). Requires image storage (Supabase Storage) and a comparison UI. | P58: 46167
A59: F-055 | B59: Design brief creation | C59: create_mode | D59: Generate a design brief document from the Forensic Canvas + selected positioning angle. Output briefs creative work (image, video, packaging) for designers or agencies. | E59: Beta | F59: P1 | G59: not_started | H59: 0 | J59: Matthew | K59: F-008,F-053 | L59: P-004,P-006,P-008 | M59: 32 | N59: 0 | O59: Sibling to F-020 (Amazon listing copy) and F-021 (Brand Voice Guide). Bridges the canvas to creative work. Required to make F-054 actionable (gap → brief → asset). | P59: 46167
A60: F-056 | B60: Image generation — deliberate non-goal | C60: create_mode | D60: NOT building. Deliberate non-goal: position IDEA as the brand brief upstream of image tools like Pixii — 'build your brand brief in IDEA, execute anywhere.' | E60: Post-GA | F60: P2 | G60: not_started | H60: 0 | J60: Matthew | K60: F-055 | M60: 80 | N60: 0 | O60: DECISION (2026-05-25): deliberate non-goal, not a backlog item. Image gen needs separate infra + ongoing cost and doesn't improve the core understanding product. Strategy: be the brief upstream of Pixii [Analysis 2026-05-17 'On Image Generation']. Pending Matthew formal sign-off to fully cut. | P60: 46167
A61: F-052 | B61: Lovable.dev vs existing codebase decision | C61: infrastructure | D61: Architectural decision: build Gen 3 in Lovable.dev (per Trevor) or extend existing React codebase. Critical risk per Launch Roadmap. | E61: Alpha | F61: P0 | G61: complete | H61: 100 | J61: Matthew | M61: 4 | N61: 0 | O61: RESOLVED 2026-04-23 [F 140678453]: split dev — Matthew builds backend in Claude Code, Trevor builds the marketing site in Lovable; beta stays on Lovable; ideabrandcoach.com on the same codebase/DB initially; custom server deferred until traction. R-013 downgraded to resolved. | P61: 46167
A62: F-057 | B62: Trust Gap™ Score results screen | C62: conversation | D62: Diagnostic results reframed as an aggregated Trust Gap™ Score (e.g. 73) that flags the widest-gap pillar (e.g. empathy). Same 6 questions / 4 pillars; UI + copy only, logic unchanged. | E62: Alpha | F62: P0 | G62: not_started | H62: 0 | J62: Matthew | K62: F-027 | L62: P-011 | M62: 12 | N62: 0 | O62: GEN3 (2026-05-25): the Alpha hook — the #1 thing to validate (must resonate). Underlying diagnostic logic already exists ('all of that code exists as is'); this is the score-screen reframe [F 144128256 @01:45,@05:00]. | P62: 46167
A63: F-058 | B63: The Decision Trigger™ capture (Stage 2B) | C63: avatar_builder | D63: Dedicated screen capturing the event that made the customer act today (the photograph, the comment, the wedding). Was previously only a canvas field. | E63: Alpha | F63: P0 | G63: not_started | H63: 0 | J63: Matthew | K63: F-059 | L63: P-001 | M63: 16 | N63: 0 | O63: GEN3 (2026-05-25): blue-water line #2 vs Pixii — operates at the level of WHEN the customer is ready to act, not just who they are [F 144128256 @09:13-14:50]. | P63: 46167
A64: F-059 | B64: Bridge screen (diagnostic → avatar) | C64: conversation | D64: Two screens that quote the user's empathy score and explain why building the avatar is the next step. 'A good coach wouldn't just present a score and move on.' | E64: Alpha | F64: P0 | G64: not_started | H64: 0 | J64: Matthew | K64: F-057 | L64: P-011 | M64: 10 | N64: 0 | O64: GEN3 (2026-05-25): connective tissue that turns the Trust Gap score into momentum into the avatar build [F 144128256 @07:20]. | P64: 46167
A65: F-060 | B65: The Signature (Stage-5 output) | C65: avatar_builder | D65: One-sentence customer truth — e.g. 'My customer isn't buying shampoo; they're buying the feeling of still being in control of how they age.' The output of the research stages. | E65: Alpha | F65: P0 | G65: not_started | H65: 0 | J65: Matthew | K65: F-004,F-005,F-006,F-007 | L65: P-001,P-002 | M65: 20 | N65: 0 | O65: GEN3 (2026-05-25): THE retention / word-of-mouth moment. MVP must validate this + the Trust Gap™ Score first; everything else is downstream [Analysis 2026-05-17]. A draft Signature may surface earlier at the Draft Canvas (F-003). | P65: 46167
A66: F-061 | B66: "Before State" emotional prompt screen | C66: avatar_builder | D66: Prompts the user to articulate the customer's emotional 'before' state as part of the avatar build. | E66: Alpha | F66: P1 | G66: not_started | H66: 0 | J66: Matthew | L66: P-002 | M66: 8 | N66: 0 | O66: GEN3 (2026-05-25): MVP ships static example text; AI-suggestion path deferred (see F-009) [F 144128256 @09:13]. | P66: 46167
A67: F-062 | B67: Decision Mode sliders | C67: avatar_builder | D67: Slider inputs for shopper type (Shopify 4 types), researcher-vs-gut, stakes, and loyalty — so users needn't type free text. | E67: Alpha | F67: P1 | G67: not_started | H67: 0 | J67: Matthew | L67: P-002 | M67: 14 | N67: 0 | O67: GEN3 (2026-05-25): lowers friction in the avatar build [F 144128256 @22:00-25:16]. | P67: 46167
A68: F-063 | B68: Review Lab (competitor + own review analysis) | C68: create_mode | D68: 'Research mode' that analyses competitor and own reviews. MVP = CSV / pasted-text upload (no scraping) to de-risk; AI analysis is a paid-tier feature. | E68: Beta | F68: P1 | G68: not_started | H68: 0 | J68: Matthew | K68: F-019 | L68: P-005 | M68: 32 | N68: 0 | O68: GEN3 (2026-05-25): paid-tier AI work behind the freemium gate (F-019). MVP deliberately avoids scraping [F 144128256 @16:31-18:47]. | P68: 46167
A69: F-064 | B69: Locked-but-visible canvas fields (free tier) | C69: pay_gate | D69: Non-subscribers see canvas fields locked rather than hidden, to entice signup/upgrade. | E69: Beta | F69: P0 | G69: not_started | H69: 0 | J69: Matthew | K69: F-019 | L69: P-012 | M69: 16 | N69: 0 | O69: GEN3 (2026-05-25): core freemium conversion mechanic [F 144128256 @28:50-32:01]. | P69: 46167
A70: F-065 | B70: "Skip avatar" / self-populate path | C70: canvas | D70: Lets a user skip the avatar build and self-populate the canvas, with an 'avatar not complete' reminder. | E70: Beta | F70: P2 | G70: not_started | H70: 0 | J70: Matthew | M70: 10 | N70: 0 | O70: GEN3 (2026-05-25): Matthew ambivalent — keep loosely scoped [F 144128256 @29:22]. | P70: 46167
A71: F-066 | B71: Landing-page A/B split test (ProductPinion) | C71: analytics | D71: Split-test V1 (ChatGPT-built, polished) vs V2 (Claude-built, simpler) landing pages. | E71: Alpha | F71: P1 | G71: not_started | H71: 0 | J71: Matthew | K71: F-067 | M71: 12 | N71: 0 | O71: GEN3 (2026-05-25): confirm ProductPinion supports landing-page split testing (R-019); else build scaffolding [F 140678453 @29:25-34:09]. | P71: 46167
A72: F-067 | B72: Marketing site on ideabrandcoach.com (same codebase/DB) | C72: infrastructure | D72: Public marketing site; app gated, revealing feature sets as they become beta-ready. Same codebase/DB initially. | E72: Alpha | F72: P0 | G72: not_started | H72: 0 | J72: Matthew | M72: 24 | N72: 0 | O72: GEN3 (2026-05-25): old consultancy site expires June. Trevor owns this track in Lovable (split-dev, F-052) [F 140691318 @00:19,@00:42]. | P72: 46167

Sheet Sub-features
A1: Sub-features — shippable units per feature
A2: subfeature_id | B2: parent_feature_id | C2: subfeature_name | D2: description | E2: acceptance_criteria | F2: status | G2: percent_complete | H2: effort_estimate_hours | I2: actual_hours | J2: blocker | K2: notes
A3: F-001.1 | B3: F-001 | C3: 10-question script in Trevor's voice | D3: Source the 10 Layer 1 questions and Trevor-voice phrasing from IDEA_KNOWLEDGE.md. | E3: All 10 questions stored in prompt config and rendered in order; Trevor reviews sample transcript. | F3: not_started | G3: 5 | H3: 8 | I3: 0 | K3: Trevor persona prompt exists (idea-framework-consultant-claude/prompt.ts) and FIELD_QUESTIONS bank has 110 candidates (src/config/fieldQuestions.ts), but no 10-question script, no fixed rendering order, getFieldQuestion() is dead code.
A4: F-001.2 | B4: F-001 | C4: Fallback responses for empty / off-topic input | D4: When the user's reply doesn't extract a field, surface a Trevor-voice nudge instead of restating the question. | E4: Off-topic input triggers fallback string; fallbacks vary by question; no robotic 'Please answer the question.' | F4: not_started | G4: 10 | H4: 6 | I4: 0 | K4: Two empty-response fallbacks exist (edge function stream.ts:129-137 + ChatService:166-173) but they trigger on 'no text', not off-topic. No per-question fallback variation, no Trevor-voice phrasing.
A5: F-001.3 | B5: F-001 | C5: Conversation state persistence | D5: Layer 1 progress persists across reload via existing FieldSyncService. | E5: Refreshing mid-conversation resumes at the last unanswered question with prior answers visible. | F5: in_progress | G5: 70 | H5: 6 | I5: 0 | K5: Session + message + chapter-progress persistence all work and survive refresh (useChatSessions, useChat, useChapterProgress); missing piece is an explicit 'last unanswered question' pointer (free-form conversation has no scripted position to resume to).
A6: F-001.4 | B6: F-001 | C6: Streaming response rendering | D6: Assistant replies stream token-by-token via SSE. | E6: User sees streaming text within 500ms of submit; SSE error states render a Trevor-voice fallback. | F6: in_progress | G6: 65 | H6: 8 | I6: 0 | K6: Streaming pipeline (edge SSE → ChatStreamParser → React state → ChatMessageList) is wired end-to-end and works; SSE-error-to-Trevor-voice fallback NOT met (errors render as generic destructive toast). No <500ms latency assertion.
A7: F-001.5 | B7: F-001 | C7: Mobile keyboard / viewport handling | D7: Conversation UI works on mobile without keyboard-induced layout breaks. | E7: iOS Safari and Android Chrome both render correctly with keyboard open; input stays visible. | F7: in_progress | G7: 25 | H7: 6 | I7: 0 | K7: Basic mobile-friendly touch targets, pb-safe padding, and 16px font (avoids iOS zoom) in ChatInputBar; missing VisualViewport API usage, keyboard-show scroll-into-view, and no cross-device validation.
A8: F-002.1 | B8: F-002 | C8: Subscribe sidebar to field extraction events | D8: Sidebar listens for new/updated field extractions and rerenders affected cards. | E8: Extracting a field during conversation updates the corresponding sidebar card within 1s. | F8: in_progress | G8: 80 | H8: 8 | I8: 0 | K8: Field-extraction events flow edge SSE → useChat → useFieldExtractionOrchestrator → ChapterSectionAccordion (auto-expands affected chapter, surfaces pending ghost values); behaviour-complete but no latency test and applied via 'pending ghost' rather than direct write.
A9: F-002.2 | B9: F-002 | C9: Confidence-score badges on sidebar fields | D9: Each populated sidebar field shows the quality / confidence badge (already shipped for V2 — port to Layer 1). | E9: Low-confidence fields show amber badge; high-confidence shows green; matches existing badge design. | F9: in_progress | G9: 75 | H9: 4 | I9: 4 | K9: Quality badges render with tiered colors on sidebar fields (ChapterFieldSet:112-135), but they reflect value-quality heuristics (fieldQualityScore.ts word-count/specificity) rather than the AI extraction confidence score — acceptance criterion 'low-confidence amber, high-confidence green from extractor confidence' is not literally met.
A10: F-002.3 | B10: F-002 | C10: Sidebar collapse / expand on mobile | D10: Mobile users can collapse sidebar to focus on conversation. | E10: Hamburger toggle hides sidebar; state persists across navigation. | F10: in_progress | G10: 40 | H10: 4 | I10: 0 | K10: Mobile sheet overlay for chapter panel works (TwoPanelTemplate:129-141 + BookOpen-icon toggle); state is in-memory only (useState in useBrandCoachV2State), does not persist across navigation; trigger is BookOpen icon, not hamburger.
A11: F-003.1 | B11: F-003 | C11: DRAFT badge component | D11: Visual badge on Draft Canvas distinguishing it from Forensic Canvas. | E11: Badge visible above-fold on canvas page; uses gold / amber tone from design tokens. | F11: not_started | G11: 0 | H11: 4 | I11: 0 | K11: No DRAFT badge component. Tier distinction is conceptual only — grep across src/ + edge functions for 'DRAFT'/'tier'/'forensic' returns ~zero structural hits. Gold/amber tokens exist (hsl(var(--gold-warm))) as mount-ready primitives.
A12: F-003.2 | B12: F-003 | C12: Synthesis edge function with Trevor prompt | D12: canvas-synthesis edge function takes Layer 1 transcript + extracted fields, returns Draft Canvas JSON. | E12: Returns all Draft-tier fields populated; fields with low confidence flagged; latency <8s. | F12: in_progress | G12: 55 | H12: 12 | I12: 0 | K12: Per-section synthesis with Trevor voice (generate-brand-strategy-section + voice.ts TREVOR_VOICE_DIRECTIVE on Haiku) exists but generates the full document — no Draft-tier subset, no low-confidence flagging, no <8s latency guarantee. Reusable as Draft once a tier filter is added.
A13: F-003.3 | B13: F-003 | C13: Forensic upgrade CTA | D13: Draft Canvas surfaces a prominent CTA inviting user into the Avatar Builder. | E13: CTA visible in canvas top-bar AND inline after the most synthesis-light section. | F13: not_started | G13: 0 | H13: 4 | I13: 0 | K13: No Forensic upgrade CTA anywhere. BrandCoachHeader and inline section locations exist as natural mount points; 'upgrade' string returns no matches in BrandCanvas.tsx/BrandCoachV2.tsx.
A14: F-003.4 | B14: F-003 | C14: Coherence pass | D14: Synthesis avoids contradictions between fields (e.g., aspirational language in one field vs jaded in another). | E14: Manual review of 5 sample draft canvases shows no contradictions; Trevor signs off. | F14: not_started | G14: 0 | H14: 4 | I14: 0 | K14: Blocked on F-003.1/F-003.2 producing a distinct Draft output to review. Trevor sign-off process not documented in repo.
... A66: F-018.3 | B66: F-018 | C66: In-app welcome screen | D66: Single-screen welcome acknowledging alpha state; names Trevor + framework. | E66: Welcome screen appears on first login; dismissable; no tutorial. | F66: in_progress | G66: 25 | H66: 2 | I66: 0 | K66: BetaWelcome page exists at /beta with 'Beta Testing Program' framing + registration form, but does NOT auto-show on first login, does NOT name Trevor or the framework, is NOT dismissable, gated by localStorage not auth.

Sheet Phase Gate
A1: Phase Gate — readiness gates by launch phase
A2: Mirrors the readiness gates from the Launch Roadmap. gate_status = MET when every mapped feature is complete.
A4: phase | B4: gate_name | C4: gate_requirement | D4: mapped_features | E4: gate_status | F4: notes
A5: Alpha | B5: Layer 1 conversation | C5: All 10 questions function end-to-end. Fallback responses written in Trevor's voice. Canvas sidebar populates in real time. | D5: F-001,F-002 | E5: =IF((COUNTIFS('Features'!$A$3:$A$72,"F-001",'Features'!$G$3:$G$72,"blocked")+COUNTIFS('Features'!$A$3:$A$72,"F-002",'Features'!$G$3:$G$72,"blocked"))>0,"BLOCKED — see mapped features",IF((COUNTIFS('Features'!$A$3:$A$72,"F-001",'Features'!$G$3:$G$72,"complete")+COUNTIFS('Features'!$A$3:$A$72,"F-002",'Features'!$G$3:$G$72,"complete"))=2,"MET","OPEN — "&(2-(COUNTIFS('Features'!$A$3:$A$72,"F-001",'Features'!$G$3:$G$72,"complete")+COUNTIFS('Features'!$A$3:$A$72,"F-002",'Features'!$G$3:$G$72,"complete")))&" of 2 remaining")) | F5: If the entry experience breaks, the tester never reaches anything else.
A6: Alpha | B6: Draft Canvas | C6: Synthesis from Layer 1 produces a coherent canvas with DRAFT badge. | D6: F-003 | E6: =IF((COUNTIFS('Features'!$A$3:$A$72,"F-003",'Features'!$G$3:$G$72,"blocked"))>0,"BLOCKED — see mapped features",IF((COUNTIFS('Features'!$A$3:$A$72,"F-003",'Features'!$G$3:$G$72,"complete"))=1,"MET","OPEN — "&(1-(COUNTIFS('Features'!$A$3:$A$72,"F-003",'Features'!$G$3:$G$72,"complete")))&" of 1 remaining")) | F6: The Draft-to-Forensic differential is the product's core demonstration of value.
A7: Alpha | B7: Avatar Builder | C7: All sections accept input, persist, and surface AI assistance modes. NB reconcile the 4 sections with the new 5-stage conversational flow ending in The Signature (F-060) — pending sign-off. | D7: F-004,F-005,F-006,F-007,F-009 | E7: =IF((COUNTIFS('Features'!$A$3:$A$72,"F-004",'Features'!$G$3:$G$72,"blocked")+COUNTIFS('Features'!$A$3:$A$72,"F-005",'Features'!$G$3:$G$72,"blocked")+COUNTIFS('Features'!$A$3:$A$72,"F-006",'Features'!$G$3:$G$72,"blocked")+COUNTIFS('Features'!$A$3:$A$72,"F-007",'Features'!$G$3:$G$72,"blocked")+COUNTIFS('Features'!$A$3:$A$72,"F-009",'Features'!$G$3:$G$72,"blocked"))>0,"BLOCKED — see mapped features",IF((COUNTIFS('Features'!$A$3:$A$72,"F-004",'Features'!$G$3:$G$72,"complete")+COUNTIFS('Features'!$A$3:$A$72,"F-005",'Features'!$G$3:$G$72,"complete")+COUNTIFS('Features'!$A$3:$A$72,"F-006",'Features'!$G$3:$G$72,"complete")+COUNTIFS('Features'!$A$3:$A$72,"F-007",'Features'!$G$3:$G$72,"complete")+COUNTIFS('Features'!$A$3:$A$72,"F-009",'Features'!$G$3:$G$72,"complete"))=5,"MET","OPEN — "&(5-(COUNTIFS('Features'!$A$3:$A$72,"F-004",'Features'!$G$3:$G$72,"complete")+COUNTIFS('Features'!$A$3:$A$72,"F-005",'Features'!$G$3:$G$72,"complete")+COUNTIFS('Features'!$A$3:$A$72,"F-006",'Features'!$G$3:$G$72,"complete")+COUNTIFS('Features'!$A$3:$A$72,"F-007",'Features'!$G$3:$G$72,"complete")+COUNTIFS('Features'!$A$3:$A$72,"F-009",'Features'!$G$3:$G$72,"complete")))&" of 5 remaining")) | F7: This is the product per Trevor's Respec.
A8: Alpha | B8: Forensic Canvas | C8: All 28+ fields render, auto-populated from Avatar data. The Decision Trigger™ displayed prominently. | D8: F-008 | E8: =IF((COUNTIFS('Features'!$A$3:$A$72,"F-008",'Features'!$G$3:$G$72,"blocked"))>0,"BLOCKED — see mapped features",IF((COUNTIFS('Features'!$A$3:$A$72,"F-008",'Features'!$G$3:$G$72,"complete"))=1,"MET","OPEN — "&(1-(COUNTIFS('Features'!$A$3:$A$72,"F-008",'Features'!$G$3:$G$72,"complete")))&" of 1 remaining")) | F8: Trevor flagged Trigger Moment as the single most important field.
A9: Alpha | B9: Manual edit lock | C9: Manually edited fields are flagged. AI never overwrites them silently. | D9: F-011 | E9: =IF((COUNTIFS('Features'!$A$3:$A$72,"F-011",'Features'!$G$3:$G$72,"blocked"))>0,"BLOCKED — see mapped features",IF((COUNTIFS('Features'!$A$3:$A$72,"F-011",'Features'!$G$3:$G$72,"complete"))=1,"MET","OPEN — "&(1-(COUNTIFS('Features'!$A$3:$A$72,"F-011",'Features'!$G$3:$G$72,"complete")))&" of 1 remaining")) | F9: Trust foundation. Existing PRD constraint.
A10: Alpha | B10: Feedback capture | C10: Three feedback moments wired. Responses route to a single sheet Matthew can monitor. | D10: F-013,F-014,F-015,F-016 | E10: =IF((COUNTIFS('Features'!$A$3:$A$72,"F-013",'Features'!$G$3:$G$72,"blocked")+COUNTIFS('Features'!$A$3:$A$72,"F-014",'Features'!$G$3:$G$72,"blocked")+COUNTIFS('Features'!$A$3:$A$72,"F-015",'Features'!$G$3:$G$72,"blocked")+COUNTIFS('Features'!$A$3:$A$72,"F-016",'Features'!$G$3:$G$72,"blocked"))>0,"BLOCKED — see mapped features",IF((COUNTIFS('Features'!$A$3:$A$72,"F-013",'Features'!$G$3:$G$72,"complete")+COUNTIFS('Features'!$A$3:$A$72,"F-014",'Features'!$G$3:$G$72,"complete")+COUNTIFS('Features'!$A$3:$A$72,"F-015",'Features'!$G$3:$G$72,"complete")+COUNTIFS('Features'!$A$3:$A$72,"F-016",'Features'!$G$3:$G$72,"complete"))=4,"MET","OPEN — "&(4-(COUNTIFS('Features'!$A$3:$A$72,"F-013",'Features'!$G$3:$G$72,"complete")+COUNTIFS('Features'!$A$3:$A$72,"F-014",'Features'!$G$3:$G$72,"complete")+COUNTIFS('Features'!$A$3:$A$72,"F-015",'Features'!$G$3:$G$72,"complete")+COUNTIFS('Features'!$A$3:$A$72,"F-016",'Features'!$G$3:$G$72,"complete")))&" of 4 remaining")) | F10: No feedback infrastructure = no learning.
A11: Alpha | B11: Error monitoring | C11: Sentry or equivalent active. Errors visible before testers report them. | D11: F-017 | E11: =IF((COUNTIFS('Features'!$A$3:$A$72,"F-017",'Features'!$G$3:$G$72,"blocked"))>0,"BLOCKED — see mapped features",IF((COUNTIFS('Features'!$A$3:$A$72,"F-017",'Features'!$G$3:$G$72,"complete"))=1,"MET","OPEN — "&(1-(COUNTIFS('Features'!$A$3:$A$72,"F-017",'Features'!$G$3:$G$72,"complete")))&" of 1 remaining"))
A12: Alpha | B12: Tester onboarding doc | C12: One-page Loom + written guide. Sets expectation that this is alpha and frames feedback constructively. | D12: F-018 | E12: =IF((COUNTIFS('Features'!$A$3:$A$72,"F-018",'Features'!$G$3:$G$72,"blocked"))>0,"BLOCKED — see mapped features",IF((COUNTIFS('Features'!$A$3:$A$72,"F-018",'Features'!$G$3:$G$72,"complete"))=1,"MET","OPEN — "&(1-(COUNTIFS('Features'!$A$3:$A$72,"F-018",'Features'!$G$3:$G$72,"complete")))&" of 1 remaining"))
A13: Alpha | B13: Architectural decision (Lovable vs existing) | C13: Decide explicitly which codebase is canonical for Gen 3. Don't half-port. | D13: F-052 | E13: =IF((COUNTIFS('Features'!$A$3:$A$72,"F-052",'Features'!$G$3:$G$72,"blocked"))>0,"BLOCKED — see mapped features",IF((COUNTIFS('Features'!$A$3:$A$72,"F-052",'Features'!$G$3:$G$72,"complete"))=1,"MET","OPEN — "&(1-(COUNTIFS('Features'!$A$3:$A$72,"F-052",'Features'!$G$3:$G$72,"complete")))&" of 1 remaining")) | F13: Risk Register: Critical. Two parallel codebases active >1 week triggers escalation.
A14: Beta | B14: Alpha findings synthesised | C14: One-page findings doc. Top 3 product gaps named. | D14: F-016 | E14: =IF((COUNTIFS('Features'!$A$3:$A$72,"F-016",'Features'!$G$3:$G$72,"blocked"))>0,"BLOCKED — see mapped features",IF((COUNTIFS('Features'!$A$3:$A$72,"F-016",'Features'!$G$3:$G$72,"complete"))=1,"MET","OPEN — "&(1-(COUNTIFS('Features'!$A$3:$A$72,"F-016",'Features'!$G$3:$G$72,"complete")))&" of 1 remaining")) | F14: Synthesis is a Matthew + Trevor activity; tracked via feedback sheet readiness.
A15: Beta | B15: Pay gate functional | C15: Stripe integrated. Both pricing options tested. Post-payment action menu wired. | D15: F-019 | E15: =IF((COUNTIFS('Features'!$A$3:$A$72,"F-019",'Features'!$G$3:$G$72,"blocked"))>0,"BLOCKED — see mapped features",IF((COUNTIFS('Features'!$A$3:$A$72,"F-019",'Features'!$G$3:$G$72,"complete"))=1,"MET","OPEN — "&(1-(COUNTIFS('Features'!$A$3:$A$72,"F-019",'Features'!$G$3:$G$72,"complete")))&" of 1 remaining")) | F15: Central conversion test of beta.
A16: Beta | B16: Create mode v1 | C16: At minimum: Amazon listing copy + Brand Voice Guide. Forensic canvas drives outputs. | D16: F-020,F-021 | E16: =IF((COUNTIFS('Features'!$A$3:$A$72,"F-020",'Features'!$G$3:$G$72,"blocked")+COUNTIFS('Features'!$A$3:$A$72,"F-021",'Features'!$G$3:$G$72,"blocked"))>0,"BLOCKED — see mapped features",IF((COUNTIFS('Features'!$A$3:$A$72,"F-020",'Features'!$G$3:$G$72,"complete")+COUNTIFS('Features'!$A$3:$A$72,"F-021",'Features'!$G$3:$G$72,"complete"))=2,"MET","OPEN — "&(2-(COUNTIFS('Features'!$A$3:$A$72,"F-020",'Features'!$G$3:$G$72,"complete")+COUNTIFS('Features'!$A$3:$A$72,"F-021",'Features'!$G$3:$G$72,"complete")))&" of 2 remaining")) | F16: Pay-gate previews need real outputs to anchor to.
A17: Beta | B17: Coach mode v1 | C17: Open conversation with full canvas as context. Document upload supported. | D17: F-022 | E17: =IF((COUNTIFS('Features'!$A$3:$A$72,"F-022",'Features'!$G$3:$G$72,"blocked"))>0,"BLOCKED — see mapped features",IF((COUNTIFS('Features'!$A$3:$A$72,"F-022",'Features'!$G$3:$G$72,"complete"))=1,"MET","OPEN — "&(1-(COUNTIFS('Features'!$A$3:$A$72,"F-022",'Features'!$G$3:$G$72,"complete")))&" of 1 remaining")) | F17: Required for the £29/mo subscription value prop.
A18: Beta | B18: Export | C18: PDF + Word for both Draft and Forensic canvases. | D18: F-023 | E18: =IF((COUNTIFS('Features'!$A$3:$A$72,"F-023",'Features'!$G$3:$G$72,"blocked"))>0,"BLOCKED — see mapped features",IF((COUNTIFS('Features'!$A$3:$A$72,"F-023",'Features'!$G$3:$G$72,"complete"))=1,"MET","OPEN — "&(1-(COUNTIFS('Features'!$A$3:$A$72,"F-023",'Features'!$G$3:$G$72,"complete")))&" of 1 remaining"))
A19: Beta | B19: Asset Inventory decision | C19: Built or formally deferred based on Alpha % flagging asset-update demand. | D19: F-028 | E19: =IF((COUNTIFS('Features'!$A$3:$A$72,"F-028",'Features'!$G$3:$G$72,"blocked"))>0,"BLOCKED — see mapped features",IF((COUNTIFS('Features'!$A$3:$A$72,"F-028",'Features'!$G$3:$G$72,"complete"))=1,"MET","OPEN — "&(1-(COUNTIFS('Features'!$A$3:$A$72,"F-028",'Features'!$G$3:$G$72,"complete")))&" of 1 remaining")) | F19: Default is NO. Decision lives in F-028 notes.
A20: Beta | B20: Analytics + funnel tracking | C20: PostHog or Mixpanel events on every funnel step. Cohort analysis possible. | D20: F-024 | E20: =IF((COUNTIFS('Features'!$A$3:$A$72,"F-024",'Features'!$G$3:$G$72,"blocked"))>0,"BLOCKED — see mapped features",IF((COUNTIFS('Features'!$A$3:$A$72,"F-024",'Features'!$G$3:$G$72,"complete"))=1,"MET","OPEN — "&(1-(COUNTIFS('Features'!$A$3:$A$72,"F-024",'Features'!$G$3:$G$72,"complete")))&" of 1 remaining"))
A21: Beta | B21: Support workflow | C21: Intercom (or email) inbox with documented SLA. | D21: F-025 | E21: =IF((COUNTIFS('Features'!$A$3:$A$72,"F-025",'Features'!$G$3:$G$72,"blocked"))>0,"BLOCKED — see mapped features",IF((COUNTIFS('Features'!$A$3:$A$72,"F-025",'Features'!$G$3:$G$72,"complete"))=1,"MET","OPEN — "&(1-(COUNTIFS('Features'!$A$3:$A$72,"F-025",'Features'!$G$3:$G$72,"complete")))&" of 1 remaining"))
A22: Beta | B22: Brand Diagnostic integration | C22: Dynamic CTA, score handoff into Layer 1, refreshed visual identity. | D22: F-027 | E22: =IF((COUNTIFS('Features'!$A$3:$A$72,"F-027",'Features'!$G$3:$G$72,"blocked"))>0,"BLOCKED — see mapped features",IF((COUNTIFS('Features'!$A$3:$A$72,"F-027",'Features'!$G$3:$G$72,"complete"))=1,"MET","OPEN — "&(1-(COUNTIFS('Features'!$A$3:$A$72,"F-027",'Features'!$G$3:$G$72,"complete")))&" of 1 remaining"))
A23: GA | B23: My Brands dashboard | C23: Multi-brand support. Users can manage 2+ brands. Brand switcher works. | D23: F-031 | E23: =IF((COUNTIFS('Features'!$A$3:$A$72,"F-031",'Features'!$G$3:$G$72,"blocked"))>0,"BLOCKED — see mapped features",IF((COUNTIFS('Features'!$A$3:$A$72,"F-031",'Features'!$G$3:$G$72,"complete"))=1,"MET","OPEN — "&(1-(COUNTIFS('Features'!$A$3:$A$72,"F-031",'Features'!$G$3:$G$72,"complete")))&" of 1 remaining"))
A24: GA | B24: Anonymous-to-authenticated migration | C24: Diagnostic completers without accounts have their data preserved when they sign up. | D24: F-032 | E24: =IF((COUNTIFS('Features'!$A$3:$A$72,"F-032",'Features'!$G$3:$G$72,"blocked"))>0,"BLOCKED — see mapped features",IF((COUNTIFS('Features'!$A$3:$A$72,"F-032",'Features'!$G$3:$G$72,"complete"))=1,"MET","OPEN — "&(1-(COUNTIFS('Features'!$A$3:$A$72,"F-032",'Features'!$G$3:$G$72,"complete")))&" of 1 remaining"))
A25: GA | B25: Self-serve onboarding | C25: Tooltip-light onboarding tour. No human needed to start. | D25: F-033 | E25: =IF((COUNTIFS('Features'!$A$3:$A$72,"F-033",'Features'!$G$3:$G$72,"blocked"))>0,"BLOCKED — see mapped features",IF((COUNTIFS('Features'!$A$3:$A$72,"F-033",'Features'!$G$3:$G$72,"complete"))=1,"MET","OPEN — "&(1-(COUNTIFS('Features'!$A$3:$A$72,"F-033",'Features'!$G$3:$G$72,"complete")))&" of 1 remaining"))
A26: GA | B26: Pricing finalised | C26: Pricing tested in beta. Tier structure final. Annual option live. | D26: F-034 | E26: =IF((COUNTIFS('Features'!$A$3:$A$72,"F-034",'Features'!$G$3:$G$72,"blocked"))>0,"BLOCKED — see mapped features",IF((COUNTIFS('Features'!$A$3:$A$72,"F-034",'Features'!$G$3:$G$72,"complete"))=1,"MET","OPEN — "&(1-(COUNTIFS('Features'!$A$3:$A$72,"F-034",'Features'!$G$3:$G$72,"complete")))&" of 1 remaining"))
A27: GA | B27: Refund policy + ToS + Privacy | C27: Standard SaaS refund (14-day no-questions). Privacy policy. Terms of service. | D27: F-037 | E27: =IF((COUNTIFS('Features'!$A$3:$A$72,"F-037",'Features'!$G$3:$G$72,"blocked"))>0,"BLOCKED — see mapped features",IF((COUNTIFS('Features'!$A$3:$A$72,"F-037",'Features'!$G$3:$G$72,"complete"))=1,"MET","OPEN — "&(1-(COUNTIFS('Features'!$A$3:$A$72,"F-037",'Features'!$G$3:$G$72,"complete")))&" of 1 remaining"))
A28: GA | B28: Status page | C28: Public uptime page. Incident communication channel. | D28: F-035 | E28: =IF((COUNTIFS('Features'!$A$3:$A$72,"F-035",'Features'!$G$3:$G$72,"blocked"))>0,"BLOCKED — see mapped features",IF((COUNTIFS('Features'!$A$3:$A$72,"F-035",'Features'!$G$3:$G$72,"complete"))=1,"MET","OPEN — "&(1-(COUNTIFS('Features'!$A$3:$A$72,"F-035",'Features'!$G$3:$G$72,"complete")))&" of 1 remaining"))
A29: GA | B29: Knowledge base | C29: 10–20 articles covering common questions from beta support. | D29: F-036 | E29: =IF((COUNTIFS('Features'!$A$3:$A$72,"F-036",'Features'!$G$3:$G$72,"blocked"))>0,"BLOCKED — see mapped features",IF((COUNTIFS('Features'!$A$3:$A$72,"F-036",'Features'!$G$3:$G$72,"complete"))=1,"MET","OPEN — "&(1-(COUNTIFS('Features'!$A$3:$A$72,"F-036",'Features'!$G$3:$G$72,"complete")))&" of 1 remaining"))
A30: GA | B30: Pricing page | C30: Pricing page that converts cold traffic. Beta tested. | D30: F-034 | E30: =IF((COUNTIFS('Features'!$A$3:$A$72,"F-034",'Features'!$G$3:$G$72,"blocked"))>0,"BLOCKED — see mapped features",IF((COUNTIFS('Features'!$A$3:$A$72,"F-034",'Features'!$G$3:$G$72,"complete"))=1,"MET","OPEN — "&(1-(COUNTIFS('Features'!$A$3:$A$72,"F-034",'Features'!$G$3:$G$72,"complete")))&" of 1 remaining"))
A31: GA | B31: Performance metrics tracking | C31: Per-avatar manual entry of ROAS, CTR, CPA, conversion rate, custom metrics. | D31: F-038 | E31: =IF((COUNTIFS('Features'!$A$3:$A$72,"F-038",'Features'!$G$3:$G$72,"blocked"))>0,"BLOCKED — see mapped features",IF((COUNTIFS('Features'!$A$3:$A$72,"F-038",'Features'!$G$3:$G$72,"complete"))=1,"MET","OPEN — "&(1-(COUNTIFS('Features'!$A$3:$A$72,"F-038",'Features'!$G$3:$G$72,"complete")))&" of 1 remaining")) | F31: OPEN QUESTION: Gen 3 spec does not address; existing V2 PRD scopes it. Treated here as GA P0 pending Matthew sign-off.
A32: Alpha | B32: Trust Gap™ Score lands | C32: Tester sees an aggregated Trust Gap™ Score + widest-gap pillar and feels it's accurate; the bridge explains why building the avatar is next. | D32: F-057,F-059 | E32: =IF((COUNTIFS('Features'!$A$3:$A$72,"F-057",'Features'!$G$3:$G$72,"blocked")+COUNTIFS('Features'!$A$3:$A$72,"F-059",'Features'!$G$3:$G$72,"blocked"))>0,"BLOCKED — see mapped features",IF((COUNTIFS('Features'!$A$3:$A$72,"F-057",'Features'!$G$3:$G$72,"complete")+COUNTIFS('Features'!$A$3:$A$72,"F-059",'Features'!$G$3:$G$72,"complete"))=2,"MET","OPEN — "&(2-(COUNTIFS('Features'!$A$3:$A$72,"F-057",'Features'!$G$3:$G$72,"complete")+COUNTIFS('Features'!$A$3:$A$72,"F-059",'Features'!$G$3:$G$72,"complete")))&" of 2 remaining")) | F32: The #1 thing to validate (Trevor). If the score doesn't resonate, nothing downstream matters.
A33: Alpha | B33: The Signature | C33: Tester produces a one-sentence Signature they recognise as true and had not previously articulated. | D33: F-060 | E33: =IF((COUNTIFS('Features'!$A$3:$A$72,"F-060",'Features'!$G$3:$G$72,"blocked"))>0,"BLOCKED — see mapped features",IF((COUNTIFS('Features'!$A$3:$A$72,"F-060",'Features'!$G$3:$G$72,"complete"))=1,"MET","OPEN — "&(1-(COUNTIFS('Features'!$A$3:$A$72,"F-060",'Features'!$G$3:$G$72,"complete")))&" of 1 remaining")) | F33: The retention / word-of-mouth moment. Validate alongside the Trust Gap Score, before everything else.
A34: Alpha | B34: The Decision Trigger™ captured | C34: A dedicated screen captures the event that made the customer act today ('why today'). | D34: F-058 | E34: =IF((COUNTIFS('Features'!$A$3:$A$72,"F-058",'Features'!$G$3:$G$72,"blocked"))>0,"BLOCKED — see mapped features",IF((COUNTIFS('Features'!$A$3:$A$72,"F-058",'Features'!$G$3:$G$72,"complete"))=1,"MET","OPEN — "&(1-(COUNTIFS('Features'!$A$3:$A$72,"F-058",'Features'!$G$3:$G$72,"complete")))&" of 1 remaining")) | F34: Blue-water line #2 vs Pixii — operates at the level of WHEN, not just who.
A35: Alpha | B35: Marketing site live (gated) | C35: ideabrandcoach.com is live; the app is gated, revealing feature sets as they become beta-ready. | D35: F-067 | E35: =IF((COUNTIFS('Features'!$A$3:$A$72,"F-067",'Features'!$G$3:$G$72,"blocked"))>0,"BLOCKED — see mapped features",IF((COUNTIFS('Features'!$A$3:$A$72,"F-067",'Features'!$G$3:$G$72,"complete"))=1,"MET","OPEN — "&(1-(COUNTIFS('Features'!$A$3:$A$72,"F-067",'Features'!$G$3:$G$72,"complete")))&" of 1 remaining")) | F35: Old consultancy site expires June; Trevor owns this track in Lovable (split-dev).

Sheet Brand Needs
A1: Brand Needs — concrete user needs mapped to features
A2: Anchors the feature inventory to real brand use cases. Each leaf need maps to one or more feature ids. fulfilment_status is derived: MET if all mapped features complete, BLOCKED if any are blocked, otherwise OPEN with count.
A4: need_id | B4: brand | C4: need | D4: mapped_features | E4: fulfilment_status | F4: notes
A5: N-001 | B5: InfinityVault | C5: Create brand strategy doc using the Coach for the 'collector' avatar | D5: F-001,F-004,F-005,F-006,F-007,F-008,F-022,F-023 | E5: =IF((COUNTIFS('Features'!$A$3:$A$72,"F-001",'Features'!$G$3:$G$72,"blocked")+COUNTIFS('Features'!$A$3:$A$72,"F-004",'Features'!$G$3:$G$72,"blocked")+COUNTIFS('Features'!$A$3:$A$72,"F-005",'Features'!$G$3:$G$72,"blocked")+COUNTIFS('Features'!$A$3:$A$72,"F-006",'Features'!$G$3:$G$72,"blocked")+COUNTIFS('Features'!$A$3:$A$72,"F-007",'Features'!$G$3:$G$72,"blocked")+COUNTIFS('Features'!$A$3:$A$72,"F-008",'Features'!$G$3:$G$72,"blocked")+COUNTIFS('Features'!$A$3:$A$72,"F-022",'Features'!$G$3:$G$72,"blocked")+COUNTIFS('Features'!$A$3:$A$72,"F-023",'Features'!$G$3:$G$72,"blocked"))>0,"BLOCKED — see mapped features",IF((COUNTIFS('Features'!$A$3:$A$72,"F-001",'Features'!$G$3:$G$72,"complete")+COUNTIFS('Features'!$A$3:$A$72,"F-004",'Features'!$G$3:$G$72,"complete")+COUNTIFS('Features'!$A$3:$A$72,"F-005",'Features'!$G$3:$G$72,"complete")+COUNTIFS('Features'!$A$3:$A$72,"F-006",'Features'!$G$3:$G$72,"complete")+COUNTIFS('Features'!$A$3:$A$72,"F-007",'Features'!$G$3:$G$72,"complete")+COUNTIFS('Features'!$A$3:$A$72,"F-008",'Features'!$G$3:$G$72,"complete")+COUNTIFS('Features'!$A$3:$A$72,"F-022",'Features'!$G$3:$G$72,"complete")+COUNTIFS('Features'!$A$3:$A$72,"F-023",'Features'!$G$3:$G$72,"complete"))=8,"MET","OPEN — "&(8-(COUNTIFS('Features'!$A$3:$A$72,"F-001",'Features'!$G$3:$G$72,"complete")+COUNTIFS('Features'!$A$3:$A$72,"F-004",'Features'!$G$3:$G$72,"complete")+COUNTIFS('Features'!$A$3:$A$72,"F-005",'Features'!$G$3:$G$72,"complete")+COUNTIFS('Features'!$A$3:$A$72,"F-006",'Features'!$G$3:$G$72,"complete")+COUNTIFS('Features'!$A$3:$A$72,"F-007",'Features'!$G$3:$G$72,"complete")+COUNTIFS('Features'!$A$3:$A$72,"F-008",'Features'!$G$3:$G$72,"complete")+COUNTIFS('Features'!$A$3:$A$72,"F-022",'Features'!$G$3:$G$72,"complete")+COUNTIFS('Features'!$A$3:$A$72,"F-023",'Features'!$G$3:$G$72,"complete")))&" of 8 remaining")) | F5: End-to-end happy path: Layer 1 conversation → Avatar Builder (collector) → Forensic Canvas → Coach refinement → Export. Validates the core product loop with a real brand.
A6: N-002 | B6: InfinityVault | C6: Assess current set of images and videos | D6: F-054 | E6: =IF((COUNTIFS('Features'!$A$3:$A$72,"F-054",'Features'!$G$3:$G$72,"blocked"))>0,"BLOCKED — see mapped features",IF((COUNTIFS('Features'!$A$3:$A$72,"F-054",'Features'!$G$3:$G$72,"complete"))=1,"MET","OPEN — "&(1-(COUNTIFS('Features'!$A$3:$A$72,"F-054",'Features'!$G$3:$G$72,"complete")))&" of 1 remaining")) | F6: Top-level need under which the gap-identification and emotional-connection needs sit.
A7: N-002.1 | B7: InfinityVault | C7: Identify what's missing in the current image/video set | D7: F-054 | E7: =IF((COUNTIFS('Features'!$A$3:$A$72,"F-054",'Features'!$G$3:$G$72,"blocked"))>0,"BLOCKED — see mapped features",IF((COUNTIFS('Features'!$A$3:$A$72,"F-054",'Features'!$G$3:$G$72,"complete"))=1,"MET","OPEN — "&(1-(COUNTIFS('Features'!$A$3:$A$72,"F-054",'Features'!$G$3:$G$72,"complete")))&" of 1 remaining")) | F7: Gap analysis on visual assets — requires side-by-side comparison + tagging against the canvas.
A8: N-002.1.1 | B8: InfinityVault | C8: Surface opportunities to improve emotional connection with the customer | D8: F-006,F-007,F-054,F-055 | E8: =IF((COUNTIFS('Features'!$A$3:$A$72,"F-006",'Features'!$G$3:$G$72,"blocked")+COUNTIFS('Features'!$A$3:$A$72,"F-007",'Features'!$G$3:$G$72,"blocked")+COUNTIFS('Features'!$A$3:$A$72,"F-054",'Features'!$G$3:$G$72,"blocked")+COUNTIFS('Features'!$A$3:$A$72,"F-055",'Features'!$G$3:$G$72,"blocked"))>0,"BLOCKED — see mapped features",IF((COUNTIFS('Features'!$A$3:$A$72,"F-006",'Features'!$G$3:$G$72,"complete")+COUNTIFS('Features'!$A$3:$A$72,"F-007",'Features'!$G$3:$G$72,"complete")+COUNTIFS('Features'!$A$3:$A$72,"F-054",'Features'!$G$3:$G$72,"complete")+COUNTIFS('Features'!$A$3:$A$72,"F-055",'Features'!$G$3:$G$72,"complete"))=4,"MET","OPEN — "&(4-(COUNTIFS('Features'!$A$3:$A$72,"F-006",'Features'!$G$3:$G$72,"complete")+COUNTIFS('Features'!$A$3:$A$72,"F-007",'Features'!$G$3:$G$72,"complete")+COUNTIFS('Features'!$A$3:$A$72,"F-054",'Features'!$G$3:$G$72,"complete")+COUNTIFS('Features'!$A$3:$A$72,"F-055",'Features'!$G$3:$G$72,"complete")))&" of 4 remaining")) | F8: Connects Emotional Journey Mapping (Avatar Builder Sec 3) + Voice of Customer (Sec 4) to the asset gaps surfaced by F-054, with design briefs (F-055) closing the loop into action.

Sheet Risks
A1: Risks — register with current state
A3: risk_id | B3: risk_name | C3: phase_exposed | D3: severity | E3: current_state | F3: trigger_threshold | G3: mitigation_owner | H3: mitigation_status | I3: notes
A4: R-001 | B4: Product doesn't solve enough user problems well enough to earn value | C4: All | D4: Critical | E4: monitoring | F4: At Alpha exit, the Trust Gap™ Score does NOT resonate (testers don't feel the gap is real/accurate) OR The Signature does NOT surprise testers with its accuracy — i.e. fewer than 2 of {P-011 Diagnostic, P-001 Signature/articulation, P-003 strategy doc} verified PARTIAL+ via tester debriefs; OR <50% of testers can articulate one concrete way the canvas changed how they think about their customer; OR fewer than 60% of shipped features map to ≥1 problem. | G4: Matthew | H4: Problems sheet operationalises tracking. Alpha feedback Moments 1 + 2 measure perceived value directly. If signal is low at Alpha midpoint, narrow scope to deepen 1-2 problems rather than adding features. GEN3 (2026-05-25): Trevor's two MVP-critical problems are the Trust Gap™ Score (P-011) and The Signature (P-001) — test those first [Analysis 2026-05-17]. ~2-3yr defensibility window → ship Alpha fast, don't gold-plate; full strategic frame in the Launch Roadmap Overview. | I4: Meta-risk above R-004 (form not conversation) and R-008 (no testimonials). The failure mode where every feature ships on time but the product still doesn't matter to anyone. Operational tool: the Problems sheet — every feature should tag to at least one problem.
A5: R-002 | B5: Alpha testers don't complete the flow | C5: Alpha | D5: High | E5: monitoring | F5: <5 of 8 complete full flow by day 7 | G5: Matthew | H5: Pre-flight QA checklist + daily monitoring + aggressive debrief follow-up planned
A6: R-003 | B6: Trevor's voice doesn't land for younger demographic | C6: Alpha | D6: Medium | E6: monitoring | F6: 3+ testers flag 'sounds old' or 'corporate' | G6: Trevor | H6: Mixed-experience tester pool; tone question in feedback Moment 1
A7: R-004 | B7: Avatar Builder feels like a form not a conversation | C7: Alpha | D7: High | E7: monitoring | F7: Any tester says 'this is just a long form' | G7: Matthew | H7: F-009 AI assistance wired before alpha; F-010 progressive disclosure tested; question phrasing reviewed by Trevor | I7: Kills Trevor's core thesis if it materialises. Specific symptom of R-001.
A8: R-005 | B8: Pay gate conversion too low | C8: Beta | D8: High | E8: monitoring | F8: <8% Draft viewers convert at 4-week mark | G8: Matthew | H8: Pay-gate previews use actual canvas data; pricing differentiated by job not features; A/B test framing
A9: R-006 | B9: Refund rate is high | C9: Beta | D9: Medium | E9: monitoring | F9: >10% refund rate | G9: Matthew | H9: Forensic canvas over-delivers vs pay-gate promise; 14-day refund window
A10: R-007 | B10: Asset tracking sucks Beta scope dry | C10: Beta | D10: Medium | E10: monitoring | F10: Builder spending >2 weeks on asset tracking in beta phase | G10: Matthew | H10: Decision gate at end of Alpha with hard threshold; v1 only if shipped
A11: R-008 | B11: ROI testimonials don't materialise | C11: Beta | D11: High | E11: monitoring | F11: <3 testimonials by week 4 of beta | G11: Matthew | H11: Testimonial harvest sequence baked in from day 1; results-focused user selection | I11: Kills the marketing engine if it materialises. Downstream symptom of R-001.
A12: R-009 | B12: GA acquisition CAC too high | C12: GA | D12: High | E12: monitoring | F12: Paid CAC payback >4 months after 30 days of spend | G12: Matthew | H12: Build organic foundation in beta; don't scale paid until CAC payback known
A13: R-010 | B13: Retention below unit economics floor | C13: GA | D13: Critical | E13: monitoring | F13: <50% retention at week 4 | G13: Matthew | H13: Retention motion built before GA; quarterly Voice of Customer refresh designed in
A14: R-011 | B14: TikTok algorithm de-prioritises long-form B2B content | C14: Post-GA | D14: Medium | E14: monitoring | F14: Organic engagement <2% after 30 days of content | G14: Matthew | H14: Organic test before paid; cap spend at £500/wk in test phase
A15: R-012 | B15: Trevor's bandwidth limits content production | C15: All | D15: Medium | E15: monitoring | F15: Trevor unavailable >2 weeks consecutively | G15: Matthew | H15: Batch recording; async content review; develop a second voice as backup
A16: R-013 | B16: Lovable.dev vs existing codebase architectural collision | C16: Alpha | D16: Low | E16: resolved | F16: Two parallel codebases active >1 week | G16: Matthew | H16: RESOLVED — split-dev decision recorded (F-052) | I16: RESOLVED 2026-04-23 [F 140678453]: split dev — Matthew builds backend in Claude Code, Trevor builds the marketing site in Lovable; beta stays on Lovable; custom server deferred until traction. Downgraded Critical→Low.
A17: R-014 | B17: Competitor launches similar tool (StoryBrand framework / Pixii execution) | C17: Beta | D17: Medium | E17: monitoring | F17: Competitor announcement or feature ship | G17: Matthew | H17: Speed; first-mover positioning on the Forensic Avatar Builder; lean into the Voice of Customer differentiator | I17: Two distinct vectors: StoryBrand (framework competitor) and Pixii (execution/image tool with a strategy layer). GEN3 (2026-05-25): 5 blue-water lines vs Pixii — (1) evidence vs inference, (2) The Decision Trigger™, (3) Trust Gap™ Diagnostic, (4) Coach as a live briefing not a one-shot PDF, (5) framework ownership. Position upstream of Pixii ('build the brief in IDEA, execute anywhere'), not as a competitor [Analysis 2026-05-17].
A18: R-015 | B18: Trevor changes framework spec mid-build | C18: All | D18: High | E18: monitoring | F18: Any framework field change requested post-Alpha launch | G18: Matthew | H18: Lock the v2 Brief; require written sign-off on changes; version-tag the build
A19: R-016 | B19: Single-developer velocity / availability | C19: All | D19: High | E19: monitoring | F19: No app progress in any 2-week window; another deadline slips | G19: Matthew | H19: Lock a small hard Alpha scope; timebox; Trevor owns the marketing-site track in parallel | I19: GEN3 (2026-05-25): the dominant live risk. Matthew is repeatedly pulled to higher-paying work; the May-1 beta target was already missed and the project is in a re-planning holding pattern [WA 2026-01-23,02-20,04-18,05-13..16].
A20: R-017 | B20: Knowledge-storage architecture undecided | C20: Alpha | D20: Medium | E20: monitoring | F20: KB work blocks F-049 / coach grounding | G20: Matthew | H20: Pick one for Alpha; defer 'offer both'; spike before committing | I20: Knowledge-graph vs spreadsheet vs Obsidian; 'where does the KB sit — Supabase?' [WA 2026-04-24,05-19].
A21: R-018 | B21: Titan conflict-of-interest | C21: Beta | D21: Medium | E21: monitoring | F21: Titan declines or restricts promotion | G21: Matthew | H21: Resolve with Dan/Titan before relying on that channel; line up alternative beta sources | I21: Athena said Trevor 'can't promote this to members', yet the beta targets the Titan AI work party [F 140678453 @31:30].
A22: R-019 | B22: ProductPinion may not support landing-page A/B | C22: Alpha | D22: Low | E22: monitoring | F22: Capability unconfirmed at site launch | G22: Trevor | H22: Trevor confirms with ProductPinion contact; else build split-test scaffolding (F-066) | I22: ProductPinion may only support listing A/B, not landing-page split testing [F 140678453 @34:09].

Sheet Change Log
A1: Change Log — append-only
A3: date | B3: who | C3: what_changed | D3: reason
A4: 2025-11-22 | B4: Matthew ↔ Trevor (WhatsApp) | C4: Core thesis: get brand owners to switch from ChatGPT to the app (work gets lost in threads) | D4: Area(s): conversation | Source: WhatsApp 2025-11-22.
A5: 2025-11-27 | B5: Matthew ↔ Trevor (WhatsApp) | C5: Pre-fill fields from users' existing brand docs (initially via a NotebookLM template) rather than re-typing | D5: Area(s): avatar_builder, infrastructure | Source: WhatsApp 2025-11-27.
A6: 2025-12-15 | B6: Matthew ↔ Trevor (WhatsApp) | C6: Data model → per-user AND per-brand separation (triggered by the coach conflating two brands) | D6: Area(s): infrastructure, accounts, coach_mode | Source: WhatsApp 2025-12-15.
A7: 2025-12-19 | B7: Matthew ↔ Trevor (WhatsApp) | C7: Brand Canvas = central synthesis layer pulling from all modules | D7: Area(s): canvas | Source: WhatsApp 2025-12-19.
A8: 2025-12-25 | B8: Matthew ↔ Trevor (WhatsApp) | C8: System Knowledge Base (vector store) seeded with Trevor's book; RAG-grounded | D8: Area(s): infrastructure, coach_mode | Source: WhatsApp 2025-12-25.
A9: 2026-01-16 | B9: Matthew ↔ Trevor (WhatsApp) | C9: Beta-Ready Scope formalized ($1000/Phase 1): Insight Module + Approval Gate + single unified strategy doc; billing deferred | D9: Area(s): multi | Source: WhatsApp 2026-01-16.
A10: 2026-01-26 | B10: Matthew ↔ Trevor (WhatsApp) | C10: Cut non-functional pages — every page must produce an output | D10: Area(s): design_system | Source: WhatsApp 2026-01-26.
A11: 2026-02-21 | B11: Matthew ↔ Trevor (WhatsApp) | C11: Trevor freezes scope: 'no additional features, speed is priority' | D11: Area(s): all | Source: WhatsApp 2026-02-21.
A12: 2026-03-01 | B12: Matthew ↔ Trevor (WhatsApp) | C12: Positioning: authority on branding/avatar/messaging + results tracking; don't compete on content generation | D12: Area(s): strategy | Source: WhatsApp 2026-03-01.
A13: 2026-03-18 | B13: Matthew ↔ Trevor (WhatsApp) | C13: 3-tier commercial model (App / Brand Community / 1:1 Consultancy); Agentic Commerce / AVM module idea | D13: Area(s): create_mode | Source: WhatsApp 2026-03-18.
A14: 2026-04-06 | B14: Matthew ↔ Trevor (WhatsApp) | C14: Migrate AI backend OpenAI → Anthropic/Claude (cost + maintainability) | D14: Area(s): infrastructure | Source: WhatsApp 2026-04-06.
... A25: 2026-05-25 | B25: Matthew (via Claude Code) | C25: Folded in Context Delta 2026-05-25 + v2 Launch Roadmap (WhatsApp + Gen 3 Fathom transcripts) | D25: Added F-057..F-067; freemium reframe (F-019); F-052/R-013 resolved (split dev, 4/23); F-056 → deliberate non-goal; added R-016..R-019; reconciled Avatar Builder 4→5 stages (flagged); added P-011/P-012; sharpened R-001 to the Trust Gap + Signature validation bar; named StoryBrand + Pixii in R-014; added Alpha gates for Trust Gap / Signature / Decision Trigger; seeded the dated decision trail.
